[
    {
        "name": "Masjid Alamgir",
        "main_category": "Mosque",
        "address": "J7JX+3RJ Masjid Alamgir, Chander Vihar, Mandawali, Delhi, 110092",
        "detailed_address": {
            "ward": "Chander Vihar, Mandawali",
            "street": "J7JX+3RJ",
            "city": "Delhi",
            "postal_code": "110092",
            "state": "Delhi",
            "country_code": "IN"
        },
        "images": [
            {
                "about": "All",
                "link": "https://lh5.googleusercontent.com/p/AF1QipP1oqFNYlYtA-GR_u9-yjz6-EhO1cSDHudy-b1P=w397-h298-k-no"
            },
            {
                "about": "Street View & 360deg",
                "link": "https://streetviewpixels-pa.googleapis.com/v1/thumbnail?panoid=zwPHYCqMjtq9TQshM9sD6Q&cb_client=maps_sv.tactile.gps&w=224&h=298&yaw=262.4517&pitch=0&thumbfov=100"
            }
        ],
        "link": "https://www.google.com/maps/place/Masjid+Alamgir/data=!4m7!3m6!1s0x390ce4b2c703570d:0x6f2c487fe7e826f7!8m2!3d28.6302064!4d77.2995165!16s%2Fg%2F11bw20w5bk!19sChIJDVcDx7LkDDkR9ybo539ILG8?authuser=0&hl=en&rclk=1",
        "coordinates": {
            "latitude": 28.6302064,
            "longitude": 77.2995165
        }
    },
    {
        "name": "Bazar Wali Masjid",
        "main_category": "Mosque",
        "address": "V58C+JMP Bazar Wali Masjid, Lalganj, Bihar 844121",
        "detailed_address": {
            "ward": null,
            "street": "V58C+JMP",
            "city": "Lalganj",
            "postal_code": "844121",
            "state": "Bihar",
            "country_code": "IN"
        },
        "images": [
            {
                "about": "All",
                "link": "https://lh5.googleusercontent.com/p/AF1QipPDsiamZGasx6GWV895IzCvGvOh_NcOVwDmt-pR=w397-h298-k-no"
            },
            {
                "about": "Street View & 360deg",
                "link": "https://streetviewpixels-pa.googleapis.com/v1/thumbnail?panoid=XxbqIlyK6sHUHc25fDcPlA&cb_client=maps_sv.tactile.gps&w=224&h=298&yaw=214.8883&pitch=0&thumbfov=100"
            },
            {
                "about": "Videos",
                "link": "https://lh5.googleusercontent.com/p/AF1QipOoTq9e77TCVT3r1b5Vc5X6ScPIJW3kMYGq0_85=w224-h407-k-no"
            }
        ],
        "link": "https://www.google.com/maps/place/Bazar+Wali+Masjid/data=!4m7!3m6!1s0x39ed441e29a6090b:0x8b45a921e906a0ad!8m2!3d25.8665963!4d85.1717098!16s%2Fg%2F11gfgrcx2y!19sChIJCwmmKR5E7TkRraAG6SGpRYs?authuser=0&hl=en&rclk=1",
        "coordinates": {
            "latitude": 25.866596299999998,
            "longitude": 85.1717098
        }
    },
    {
        "name": "Lalganj Mosque",
        "main_category": "Mosque",
        "address": "Lalganj Mosque, Lalganj Rd, Mairwa, Lalganj, Bihar 841239",
        "detailed_address": {
            "ward": null,
            "street": "Lalganj Rd",
            "city": "Mairwa, Lalganj",
            "postal_code": "841239",
            "state": "Bihar",
            "country_code": "IN"
        },
        "images": [
            {
                "about": "All",
                "link": "https://lh5.googleusercontent.com/p/AF1QipOQSoB28O9wTE_aC67ABKTIsj4DYabqyg4vEsPv=w224-h298-k-no"
            },
            {
                "about": "By owner",
                "link": "https://lh5.googleusercontent.com/p/AF1QipOCu0F85LlCPHZpFaCj4erGMpPoPjD637O49eiU=w529-h298-k-no"
            },
            {
                "about": "Videos",
                "link": "https://lh5.googleusercontent.com/p/AF1QipMp_z9rgfc801bklDKe1sKhb2-pmN1D3NeKtZIH=w224-h398-k-no"
            }
        ],
        "link": "https://www.google.com/maps/place/Lalganj+Mosque/data=!4m7!3m6!1s0x399253b526956c33:0x1bc0f6c56f94acea!8m2!3d26.2321851!4d84.1444819!16s%2Fg%2F11g6xnpvmh!19sChIJM2yVJrVTkjkR6qyUb8X2wBs?authuser=0&hl=en&rclk=1",
        "coordinates": {
            "latitude": 26.2321851,
            "longitude": 84.1444819
        }
    },
    {
        "name": "Sunni Noori Raza Masjid Nanhopur",
        "main_category": "Mosque",
        "address": "XPM4+R8V Sunni Noori Raza Masjid Nanhopur, Lalganj - Ghuisarnath Rd, Pure Murli, Uttar Pradesh 230132",
        "detailed_address": {
            "ward": null,
            "street": "XPM4+R8V, Lalganj - Ghuisarnath Rd",
            "city": "Pure Murli",
            "postal_code": "230132",
            "state": "Uttar Pradesh",
            "country_code": "IN"
        },
        "images": [
            {
                "about": "All",
                "link": "https://lh5.googleusercontent.com/p/AF1QipPM0L5ucnKfdXfMNLpXlgGI9Ujo3J21kI-GMU_6=w224-h398-k-no"
            }
        ],
        "link": "https://www.google.com/maps/place/Sunni+Noori+Raza+Masjid+Nanhopur/data=!4m7!3m6!1s0x399aefe4440740a5:0x29c6fcab795fdfd7!8m2!3d25.9846024!4d81.7058051!16s%2Fg%2F11c6prpym7!19sChIJpUAHROTvmjkR199feav8xik?authuser=0&hl=en&rclk=1",
        "coordinates": {
            "latitude": 25.9846024,
            "longitude": 81.70580509999999
        }
    },
    {
        "name": "Jama Masjid, Mohammadpur",
        "main_category": "Mosque",
        "address": "R7W5+JG3 Jama Masjid, Mohammadpur, Lalganj - Tinpulwa - Bhagwanpur Rd, Mohamadpur Rohua, Bihar 844114",
        "detailed_address": {
            "ward": null,
            "street": "R7W5+JG3, Lalganj - Tinpulwa - Bhagwanpur Rd",
            "city": "Mohamadpur Rohua",
            "postal_code": "844114",
            "state": "Bihar",
            "country_code": "IN"
        },
        "images": [
            {
                "about": "All",
                "link": "https://lh5.googleusercontent.com/p/AF1QipPu0Yz1QUmfgXsncpQ4PT9E1crU3kG4b63mdEDU=w224-h458-k-no"
            },
            {
                "about": "Street View & 360deg",
                "link": "https://streetviewpixels-pa.googleapis.com/v1/thumbnail?panoid=FRWu_vOzf5ngffQekBApog&cb_client=maps_sv.tactile.gps&w=224&h=298&yaw=337.1195&pitch=0&thumbfov=100"
            }
        ],
        "link": "https://www.google.com/maps/place/Jama+Masjid,+Mohammadpur/data=!4m7!3m6!1s0x39ed42132e5098d3:0xa597827e71ff452c!8m2!3d25.8465211!4d85.2588003!16s%2Fg%2F11g9n51rlm!19sChIJ05hQLhNC7TkRLEX_cX6Cl6U?authuser=0&hl=en&rclk=1",
        "coordinates": {
            "latitude": 25.8465211,
            "longitude": 85.25880029999999
        }
    },
    {
        "name": "Piyarma Mosque",
        "main_category": "Mosque",
        "address": "V5WX+8XV Piyarma Mosque, piyarma, Lalganj, Mukundpur Urf Parmanandpur, Bihar 844121",
        "detailed_address": {
            "ward": "piyarma",
            "street": "V5WX+8XV",
            "city": "Lalganj, Mukundpur Urf Parmanandpur",
            "postal_code": null,
            "state": "Bihar",
            "country_code": "IN"
        },
        "images": [
            {
                "about": "All",
                "link": "https://lh5.googleusercontent.com/p/AF1QipO1CpzJeBro-XUdJtqnSeyillo0VRpchtWWGpfs=w527-h298-k-no"
            },
            {
                "about": "Street View & 360deg",
                "link": "https://streetviewpixels-pa.googleapis.com/v1/thumbnail?panoid=eehZ6VaQlLSrCp1W5S3Tcg&cb_client=maps_sv.tactile.gps&w=224&h=298&yaw=101.92378&pitch=0&thumbfov=100"
            }
        ],
        "link": "https://www.google.com/maps/place/Piyarma+Mosque/data=!4m7!3m6!1s0x39ed4139e056b2e1:0x2c2ba8b888e89410!8m2!3d25.8958671!4d85.1999087!16s%2Fg%2F11g8g1lh0v!19sChIJ4bJW4DlB7TkREJToiLioKyw?authuser=0&hl=en&rclk=1",
        "coordinates": {
            "latitude": 25.8958671,
            "longitude": 85.1999087
        }
    },
    {
        "name": "Jama Masjid",
        "main_category": "Mosque",
        "address": "V56F+F22 Jama Masjid, Agarpur, Lalganj, Bihar 844121",
        "detailed_address": {
            "ward": "Aggarpur",
            "street": "V56F+F22, Agarpur",
            "city": "Lalganj",
            "postal_code": "844121",
            "state": "Bihar",
            "country_code": "IN"
        },
        "images": [
            {
                "about": "All",
                "link": "https://lh5.googleusercontent.com/p/AF1QipNkBjSW3Cgo3-XVQZ_SEdckni4gJ3JbSlLAm26Y=w224-h298-k-no"
            },
            {
                "about": "Dome",
                "link": "https://lh5.googleusercontent.com/p/AF1QipODQY1fZ15juFQuqVKN6tNmvrLlG_c6NqIbTCl6=w224-h298-k-no"
            },
            {
                "about": "Street View & 360deg",
                "link": "https://streetviewpixels-pa.googleapis.com/v1/thumbnail?panoid=Gr66DnbjyzArI1gp5Gyq1g&cb_client=maps_sv.tactile.gps&w=224&h=298&yaw=331.03546&pitch=0&thumbfov=100"
            }
        ],
        "link": "https://www.google.com/maps/place/Jama+Masjid/data=!4m7!3m6!1s0x39ed441eca58a1bf:0xfa2b9062e589790d!8m2!3d25.8611456!4d85.1725105!16s%2Fg%2F11gdly8n94!19sChIJv6FYyh5E7TkRDXmJ5WKQK_o?authuser=0&hl=en&rclk=1",
        "coordinates": {
            "latitude": 25.8611456,
            "longitude": 85.1725105
        }
    },
    {
        "name": "Badi Masjid",
        "main_category": "Mosque",
        "address": "5XCC+9R8 Badi Masjid, Lalganj, Alampur, Uttar Pradesh 229206",
        "detailed_address": {
            "ward": null,
            "street": "5XCC+9R8",
            "city": "Lalganj, Alampur",
            "postal_code": "229206",
            "state": "Uttar Pradesh",
            "country_code": "IN"
        },
        "images": [
            {
                "about": "All",
                "link": "https://lh5.googleusercontent.com/p/AF1QipNV5uTY2OlYdDBP3wtY71FJhG9N7om6VJhQ2G0V=w224-h398-k-no"
            },
            {
                "about": "Videos",
                "link": "https://lh5.googleusercontent.com/p/AF1QipP69nBbZ9Dgya7sRP_Q8PT7E-rU0SpkrrIa0UPp=w224-h398-k-no"
            }
        ],
        "link": "https://www.google.com/maps/place/Badi+Masjid/data=!4m7!3m6!1s0x399b82c4cafebbb5:0xe5902e7c32348ace!8m2!3d26.1709007!4d80.9720761!16s%2Fg%2F119w752j4!19sChIJtbv-ysSCmzkRzoo0MnwukOU?authuser=0&hl=en&rclk=1",
        "coordinates": {
            "latitude": 26.170900699999997,
            "longitude": 80.9720761
        }
    },
    {
        "name": "WARSI MASJID",
        "main_category": "Mosque",
        "address": "5X6C+MM5 WARSI MASJID, Allah Nagar,, Lalganj, Uttar Pradesh 229206",
        "detailed_address": {
            "ward": null,
            "street": "5X6C+MM5, Allah Nagar,",
            "city": "Lalganj, Datauli Lal Ganj",
            "postal_code": "229206",
            "state": "Uttar Pradesh",
            "country_code": "IN"
        },
        "images": [
            {
                "about": "All",
                "link": "https://lh5.googleusercontent.com/p/AF1QipPg6ct8D-UnhIEmucSpaOy_GosY8CgrUwf49ziT=w399-h298-k-no"
            },
            {
                "about": "Dome",
                "link": "https://lh5.googleusercontent.com/p/AF1QipPg6ct8D-UnhIEmucSpaOy_GosY8CgrUwf49ziT=w399-h298-k-no"
            },
            {
                "about": "Videos",
                "link": "https://lh5.googleusercontent.com/p/AF1QipN3D9cH3FzAM3D1HQaesfzYf_o5EoAOZmytF-kR=w224-h398-k-no"
            }
        ],
        "link": "https://www.google.com/maps/place/WARSI+MASJID/data=!4m7!3m6!1s0x399b82c722e2c7eb:0x4eb9157ebd20c0c9!8m2!3d26.1616371!4d80.9717208!16s%2Fg%2F11c1pgyk5k!19sChIJ68fiIseCmzkRycAgvX4VuU4?authuser=0&hl=en&rclk=1",
        "coordinates": {
            "latitude": 26.1616371,
            "longitude": 80.9717208
        }
    },
    {
        "name": "Kanch Meel Masjid",
        "main_category": "Mosque",
        "address": "5XCC+MPR Kanch Meel Masjid, Lalganj, Alampur, Uttar Pradesh 229206",
        "detailed_address": {
            "ward": null,
            "street": "5XCC+MPR",
            "city": "Lalganj, Alampur",
            "postal_code": "229206",
            "state": "Uttar Pradesh",
            "country_code": "IN"
        },
        "images": [
            {
                "about": "All",
                "link": "https://lh5.googleusercontent.com/p/AF1QipN1QZ2yc5I94_-5tQRB0Y-fUdGcloF7SXQDG7va=w224-h510-k-no"
            },
            {
                "about": "Dome",
                "link": "https://lh5.googleusercontent.com/p/AF1QipNTwsrly9mSznjlJ9LLW-UXsKKFeAWIL9Ms-DL_=w224-h510-k-no"
            },
            {
                "about": "Street View & 360deg",
                "link": "https://streetviewpixels-pa.googleapis.com/v1/thumbnail?panoid=0XNXhivjFBXvBzbKvdeUeQ&cb_client=maps_sv.tactile.gps&w=224&h=298&yaw=336.79697&pitch=0&thumbfov=100"
            }
        ],
        "link": "https://www.google.com/maps/place/Kanch+Meel+Masjid/data=!4m7!3m6!1s0x399b82db47d9531f:0x99a756793e4e6c20!8m2!3d26.1717288!4d80.9717542!16s%2Fg%2F119w13zj_!19sChIJH1PZR9uCmzkRIGxOPnlWp5k?authuser=0&hl=en&rclk=1",
        "coordinates": {
            "latitude": 26.1717288,
            "longitude": 80.97175419999999
        }
    },
    {
        "name": "JAMA MASJID",
        "main_category": "Mosque",
        "address": "5X89+2JM JAMA MASJID, Chik Mandi,, Lalganj, Uttar Pradesh 229206",
        "detailed_address": {
            "ward": null,
            "street": "5X89+2JM, Chik Mandi,",
            "city": "Lalganj",
            "postal_code": "229206",
            "state": "Uttar Pradesh",
            "country_code": "IN"
        },
        "images": [
            {
                "about": "All",
                "link": "https://lh5.googleusercontent.com/p/AF1QipPL6lhc5XrdvOFbBYE8AkVo5hVNCwp53fMd_WY9=w224-h398-k-no"
            },
            {
                "about": "Street View & 360deg",
                "link": "https://streetviewpixels-pa.googleapis.com/v1/thumbnail?panoid=1Jnynu5X5hjv_CRZ2XZ1zw&cb_client=maps_sv.tactile.gps&w=224&h=298&yaw=150.7605&pitch=0&thumbfov=100"
            }
        ],
        "link": "https://www.google.com/maps/place/JAMA+MASJID/data=!4m7!3m6!1s0x399b82c3df912f09:0x5d906d6363ffe230!8m2!3d26.1650992!4d80.9690604!16s%2Fg%2F11cr_q3tb8!19sChIJCS-R38OCmzkRMOL_Y2NtkF0?authuser=0&hl=en&rclk=1",
        "coordinates": {
            "latitude": 26.1650992,
            "longitude": 80.96906039999999
        }
    },
    {
        "name": "Chhoty Masjid (Badh Samaila) chhwtty msjd",
        "main_category": "Mosque",
        "address": "7X76+8Q3 Chhoty Masjid (Badh Samaila) chhwtty msjd, Badh Samaila, Lalganj, Bihar 847121",
        "detailed_address": {
            "ward": "Badh Samaila",
            "street": "7X76+8Q3",
            "city": "Lalganj",
            "postal_code": "847121",
            "state": "Bihar",
            "country_code": "IN"
        },
        "images": [
            {
                "about": "All",
                "link": "https://lh5.googleusercontent.com/p/AF1QipMbdk9ip4d1RNf7mjXzxtT-o8CLaacGGzBEq1RF=w397-h298-k-no"
            }
        ],
        "link": "https://www.google.com/maps/place/Chhoty+Masjid+%28Badh+Samaila%29+%DA%86%DA%BE%D9%88%D9%B9%DB%8C+%D9%85%D8%B3%D8%AC%D8%AF%E2%80%AD/data=!4m7!3m6!1s0x39edc9321c6c94ab:0xca8dae77d26f275a!8m2!3d26.2632548!4d85.9619103!16s%2Fg%2F11ft8hm_57!19sChIJq5RsHDLJ7TkRWidv0neujco?authuser=0&hl=en&rclk=1",
        "coordinates": {
            "latitude": 26.2632548,
            "longitude": 85.9619103
        }
    },
    {
        "name": "JAMA MASJID BADH SAMAILA jm` msjd brrh smyl",
        "main_category": "Mosque",
        "address": "7X76+W28 JAMA MASJID BADH SAMAILA jm` msjd brrh smyl, Badh Samaila, Lalganj, Bihar 847121",
        "detailed_address": {
            "ward": "Badh Samaila",
            "street": "7X76+W28",
            "city": "Lalganj",
            "postal_code": "847121",
            "state": "Bihar",
            "country_code": "IN"
        },
        "images": [
            {
                "about": "All",
                "link": "https://lh5.googleusercontent.com/p/AF1QipN1SDFFPE7Ju33vupSTQYfqsiZLTjA5GSR8tZG_=w397-h298-k-no"
            }
        ],
        "link": "https://www.google.com/maps/place/JAMA+MASJID+BADH+SAMAILA+%D8%AC%D8%A7%D9%85%D8%B9+%D9%85%D8%B3%D8%AC%D8%AF+%D8%A8%D8%A7%DA%91%DA%BE+%D8%B3%D9%85%DB%8C%D9%84%D8%A7%E2%80%AD/data=!4m7!3m6!1s0x39edc9e77d38da85:0x7190631059a8a6a!8m2!3d26.2647756!4d85.9600719!16s%2Fg%2F11nxt58tqf!19sChIJhdo4fefJ7TkRaoqaBTEGGQc?authuser=0&hl=en&rclk=1",
        "coordinates": {
            "latitude": 26.2647756,
            "longitude": 85.9600719
        }
    },
    {
        "name": "BAAG WALI MASJID",
        "main_category": "Mosque",
        "address": "BAAG WALI MASJID, Uttar pradesh Lalganj gandhi chauraha, Uttar Pradesh 229206",
        "detailed_address": {
            "ward": null,
            "street": "Uttar pradesh Lalganj gandhi chauraha",
            "city": "Korihara, Lalganj",
            "postal_code": "229206",
            "state": "Uttar Pradesh",
            "country_code": "IN"
        },
        "images": [
            {
                "about": "All",
                "link": "https://lh5.googleusercontent.com/p/AF1QipNKDbzN6Tc_FBbjSb2d2zO7DnpvCg3x2FxYQE64=w224-h298-k-no"
            },
            {
                "about": "By owner",
                "link": "https://lh5.googleusercontent.com/p/AF1QipNKDbzN6Tc_FBbjSb2d2zO7DnpvCg3x2FxYQE64=w224-h298-k-no"
            },
            {
                "about": "Videos",
                "link": "https://lh5.googleusercontent.com/p/AF1QipPvYVMu0kxtbegynGkt-Fe-rXQMF201sruAyf-P=w529-h298-k-no"
            },
            {
                "about": "Street View & 360deg",
                "link": "https://streetviewpixels-pa.googleapis.com/v1/thumbnail?panoid=DRFpbyRUbMkqiVzDR1kiNw&cb_client=maps_sv.tactile.gps&w=224&h=298&yaw=16.510752&pitch=0&thumbfov=100"
            }
        ],
        "link": "https://www.google.com/maps/place/BAAG+WALI+MASJID/data=!4m7!3m6!1s0x399b82c0ffc9f089:0x5fd312b389c0796!8m2!3d26.1616295!4d80.9680779!16s%2Fg%2F11g8b570_f!19sChIJifDJ_8CCmzkRlgecOCsx_QU?authuser=0&hl=en&rclk=1",
        "coordinates": {
            "latitude": 26.1616295,
            "longitude": 80.9680779
        }
    },
    {
        "name": "KADRI MASJID",
        "main_category": "Mosque",
        "address": "5X88+HWR KADRI MASJID, Ali Nagar, Lalganj, Uttar Pradesh 229206",
        "detailed_address": {
            "ward": null,
            "street": "5X88+HWR, Ali Nagar",
            "city": "Lalganj, Suddan Khera",
            "postal_code": "229206",
            "state": "Uttar Pradesh",
            "country_code": "IN"
        },
        "images": [
            {
                "about": "All",
                "link": "https://lh5.googleusercontent.com/p/AF1QipPOS0k3qJodwenZu6h9c84oXoX9USTgguzUDOLC=w298-h298-k-no"
            },
            {
                "about": "Street View & 360deg",
                "link": "https://streetviewpixels-pa.googleapis.com/v1/thumbnail?panoid=mNTxo4e_Ems_2v2KksoAcQ&cb_client=maps_sv.tactile.gps&w=224&h=298&yaw=298.11798&pitch=0&thumbfov=100"
            },
            {
                "about": "Videos",
                "link": "https://lh5.googleusercontent.com/p/AF1QipMZH5H2Eic3LdPFCB4mNvgHVbWjfnQI9_JkT7iz=w224-h398-k-no"
            }
        ],
        "link": "https://www.google.com/maps/place/KADRI+MASJID/data=!4m7!3m6!1s0x399b82c249aa4e1d:0x2bea2936cf31cf75!8m2!3d26.1664999!4d80.967257!16s%2Fg%2F11c1dj8gmz!19sChIJHU6qScKCmzkRdc8xzzYp6is?authuser=0&hl=en&rclk=1",
        "coordinates": {
            "latitude": 26.166499899999998,
            "longitude": 80.96725699999999
        }
    },
    {
        "name": "Jama Masjid, Muslim Tola, Lalganj,",
        "main_category": "Mosque",
        "address": "Jama Masjid, Muslim Tola, Lalganj,, Bishambar chowk, 2k, Lal Ganj, Bihar 854303",
        "detailed_address": {
            "ward": null,
            "street": "Bishambar chowk, 2k",
            "city": "Lal Ganj",
            "postal_code": "854303",
            "state": "Bihar",
            "country_code": "IN"
        },
        "images": [
            {
                "about": "All",
                "link": "https://streetviewpixels-pa.googleapis.com/v1/thumbnail?panoid=JhCPbf4ylmo3rHrueJaDtA&cb_client=maps_sv.tactile.gps&w=224&h=298&yaw=45.56784&pitch=0&thumbfov=100"
            },
            {
                "about": "Street View & 360deg",
                "link": "https://streetviewpixels-pa.googleapis.com/v1/thumbnail?panoid=JhCPbf4ylmo3rHrueJaDtA&cb_client=maps_sv.tactile.gps&w=224&h=298&yaw=45.56784&pitch=0&thumbfov=100"
            }
        ],
        "link": "https://www.google.com/maps/place/Jama+Masjid,+Muslim+Tola,+Lalganj,/data=!4m7!3m6!1s0x39efff32b3095a11:0xa614f57e68e31189!8m2!3d25.7319845!4d87.4808752!16s%2Fg%2F11ghp2kqgt!19sChIJEVoJszL_7zkRiRHjaH71FKY?authuser=0&hl=en&rclk=1",
        "coordinates": {
            "latitude": 25.7319845,
            "longitude": 87.4808752
        }
    },
    {
        "name": "Mosque",
        "main_category": "Mosque",
        "address": "Mosque, 4R3R+7RP, lalganj, CHHOTI, Dihlahi, Bihar 846003",
        "detailed_address": {
            "ward": null,
            "street": "4R3R+7RP, lalganj, CHHOTI",
            "city": "Dihlahi",
            "postal_code": "846003",
            "state": "Bihar",
            "country_code": "IN"
        },
        "images": [
            {
                "about": "All",
                "link": "https://lh5.googleusercontent.com/p/AF1QipNiuzgxeMz1XOeK7dpv2IpkXrePte3mgzKzreYz=w224-h351-k-no"
            }
        ],
        "link": "https://www.google.com/maps/place/Mosque/data=!4m7!3m6!1s0x39edbb73822d0777:0xdd963563a3f40d4e!8m2!3d26.103212!4d85.842085!16s%2Fg%2F11h1_0ywx_!19sChIJdwctgnO77TkRTg30o2M1lt0?authuser=0&hl=en&rclk=1",
        "coordinates": {
            "latitude": 26.103212,
            "longitude": 85.842085
        }
    },
    {
        "name": "MOHAMMADIYA MASJID",
        "main_category": "Mosque",
        "address": "5X88+WFF MOHAMMADIYA MASJID, 229206, Ali Nagar, Lalganj, Suddan Khera, Uttar Pradesh 229206",
        "detailed_address": {
            "ward": "Ali Nagar",
            "street": "5X88+WFF, 229206",
            "city": "Lalganj, Suddan Khera",
            "postal_code": null,
            "state": "Uttar Pradesh",
            "country_code": "IN"
        },
        "images": [
            {
                "about": "All",
                "link": "https://lh5.googleusercontent.com/p/AF1QipMvLalzhobhQ7Xkn1T0yJLG1TiMlGD3arhinN1T=w224-h398-k-no"
            }
        ],
        "link": "https://www.google.com/maps/place/MOHAMMADIYA+MASJID/data=!4m7!3m6!1s0x399b82c261ce234d:0x6e385c79fad6e159!8m2!3d26.1676509!4d80.9662468!16s%2Fg%2F11c4y5161h!19sChIJTSPOYcKCmzkRWeHW-nlcOG4?authuser=0&hl=en&rclk=1",
        "coordinates": {
            "latitude": 26.167650899999998,
            "longitude": 80.9662468
        }
    },
    {
        "name": "Jama Masjid (Markaz)",
        "main_category": "Mosque",
        "address": "QXVW+7F9 Jama Masjid (Markaz), Lalganj, Uttar Pradesh 276202",
        "detailed_address": {
            "ward": null,
            "street": "QXVW+7F9",
            "city": "Lalganj",
            "postal_code": "276202",
            "state": "Uttar Pradesh",
            "country_code": "IN"
        },
        "images": [
            {
                "about": "All",
                "link": "https://lh5.googleusercontent.com/p/AF1QipNQwLoIFZhMKymYjy78X3TN7xxZJqneO_bZZmJL=w397-h298-k-no"
            }
        ],
        "link": "https://www.google.com/maps/place/Jama+Masjid+%28Markaz%29/data=!4m7!3m6!1s0x3991c99f9dff0901:0xac23a2a21130a549!8m2!3d25.7931512!4d82.9962205!16s%2Fg%2F11gty_s1bz!19sChIJAQn_nZ_JkTkRSaUwEaKiI6w?authuser=0&hl=en&rclk=1",
        "coordinates": {
            "latitude": 25.7931512,
            "longitude": 82.99622049999999
        }
    },
    {
        "name": "Chand Tara Masjid",
        "main_category": "Mosque",
        "address": "WPJ3+JW7 Chand Tara Masjid, Pure Tikaram, Uttar Pradesh 230132",
        "detailed_address": {
            "ward": null,
            "street": "WPJ3+JW7",
            "city": "Pure Tikaram",
            "postal_code": "230132",
            "state": "Uttar Pradesh",
            "country_code": "IN"
        },
        "images": [
            {
                "about": "All",
                "link": "https://streetviewpixels-pa.googleapis.com/v1/thumbnail?panoid=O1Vbeq-HBzpKVs5kmsbghg&cb_client=maps_sv.tactile.gps&w=224&h=298&yaw=160.83562&pitch=0&thumbfov=100"
            },
            {
                "about": "Street View & 360deg",
                "link": "https://streetviewpixels-pa.googleapis.com/v1/thumbnail?panoid=O1Vbeq-HBzpKVs5kmsbghg&cb_client=maps_sv.tactile.gps&w=224&h=298&yaw=160.83562&pitch=0&thumbfov=100"
            }
        ],
        "link": "https://www.google.com/maps/place/Chand+Tara+Masjid/data=!4m7!3m6!1s0x399aef6e4d0f8fcf:0x46ce43bef432355a!8m2!3d25.9315379!4d81.7047886!16s%2Fg%2F11cn5fqgd_!19sChIJz48PTW7vmjkRWjUy9L5DzkY?authuser=0&hl=en&rclk=1",
        "coordinates": {
            "latitude": 25.9315379,
            "longitude": 81.7047886
        }
    },
    {
        "name": "Masjid-E-Bilal Lalganj Chauraha",
        "main_category": "Mosque",
        "address": "9RRG+MFJ Masjid-E-Bilal Lalganj Chauraha, Jakha Shiwa Pur, Uttar Pradesh 227813",
        "detailed_address": {
            "ward": null,
            "street": "9RRG+MFJ",
            "city": "Jakha Shiwa Pur",
            "postal_code": "227813",
            "state": "Uttar Pradesh",
            "country_code": "IN"
        },
        "images": [
            {
                "about": "All",
                "link": "https://lh5.googleusercontent.com/p/AF1QipOcnLF9WqJFmUDPwXDs_SHFL4Y1_Pj4vGuXd_7w=w224-h397-k-no"
            },
            {
                "about": "Street View & 360deg",
                "link": "https://streetviewpixels-pa.googleapis.com/v1/thumbnail?panoid=oo7f8aXb6VMLk9NGbECehQ&cb_client=maps_sv.tactile.gps&w=224&h=298&yaw=177.56378&pitch=0&thumbfov=100"
            }
        ],
        "link": "https://www.google.com/maps/place/Masjid-E-Bilal+Lalganj+Chauraha/data=!4m7!3m6!1s0x399a436f36e0fcf3:0xac35ec85272e4778!8m2!3d26.3917114!4d81.826142!16s%2Fg%2F11skl0zgsk!19sChIJ8_zgNm9DmjkReEcuJ4XsNaw?authuser=0&hl=en&rclk=1",
        "coordinates": {
            "latitude": 26.3917114,
            "longitude": 81.82614199999999
        }
    },
    {
        "name": "KATGHAR MASJID",
        "main_category": "Place of worship",
        "address": "R222+GJC KATGHAR MASJID, Katghar Lalganj, Uttar Pradesh 276202",
        "detailed_address": {
            "ward": null,
            "street": "R222+GJC",
            "city": "Katghar Lalganj",
            "postal_code": "276202",
            "state": "Uttar Pradesh",
            "country_code": "IN"
        },
        "images": [
            {
                "about": "All",
                "link": "https://lh5.googleusercontent.com/p/AF1QipOr0qiZrFb7jgzkxXB5QvrBh37NkYqVNQctwddh=w224-h324-k-no"
            },
            {
                "about": "Videos",
                "link": "https://lh5.googleusercontent.com/p/AF1QipM6csfd0yiHWP-CfmupY0o1TRGXTj0yqEltaNF-=w224-h398-k-no"
            }
        ],
        "link": "https://www.google.com/maps/place/KATGHAR+MASJID/data=!4m7!3m6!1s0x3991c95d7739cfe5:0x31af761a1c549787!8m2!3d25.8013073!4d83.0015121!16s%2Fg%2F11fxftlpcb!19sChIJ5c85d13JkTkRh5dUHBp2rzE?authuser=0&hl=en&rclk=1",
        "coordinates": {
            "latitude": 25.801307299999998,
            "longitude": 83.0015121
        }
    },
    {
        "name": "Katghar Jama Masjid",
        "main_category": "Mosque",
        "address": "RX2X+WXX Katghar Jama Masjid, Katghar Lalganj, Uttar Pradesh 276202",
        "detailed_address": {
            "ward": null,
            "street": "RX2X+WXX",
            "city": "Katghar Lalganj",
            "postal_code": "276202",
            "state": "Uttar Pradesh",
            "country_code": "IN"
        },
        "images": [],
        "link": "https://www.google.com/maps/place/Katghar+Jama+Masjid/data=!4m7!3m6!1s0x3991c96760c02615:0x72d6cc4d68847448!8m2!3d25.8023518!4d82.9999692!16s%2Fg%2F11gdvx6ft5!19sChIJFSbAYGfJkTkRSHSEaE3M1nI?authuser=0&hl=en&rclk=1",
        "coordinates": {
            "latitude": 25.8023518,
            "longitude": 82.9999692
        }
    },
    {
        "name": "Jama Masjid Lalganj",
        "main_category": "Place of worship",
        "address": "2985+MMJ Jama Masjid Lalganj, Lalganj, Uttar Pradesh 231211",
        "detailed_address": {
            "ward": null,
            "street": "2985+MMJ",
            "city": "Lalganj",
            "postal_code": "231211",
            "state": "Uttar Pradesh",
            "country_code": "IN"
        },
        "images": [
            {
                "about": "All",
                "link": "https://streetviewpixels-pa.googleapis.com/v1/thumbnail?panoid=HIf4jFWtcRdcFjp647Y2Ng&cb_client=maps_sv.tactile.gps&w=224&h=298&yaw=85.1915&pitch=0&thumbfov=100"
            },
            {
                "about": "Latest",
                "link": "https://lh5.googleusercontent.com/p/AF1QipOGgxGvACeudzaGQD8VC8_ZemWUTI3xMnqXCarZ=w224-h298-k-no"
            },
            {
                "about": "Street View & 360deg",
                "link": "https://streetviewpixels-pa.googleapis.com/v1/thumbnail?panoid=HIf4jFWtcRdcFjp647Y2Ng&cb_client=maps_sv.tactile.gps&w=224&h=298&yaw=85.1915&pitch=0&thumbfov=100"
            }
        ],
        "link": "https://www.google.com/maps/place/Jama+Masjid+Lalganj/data=!4m7!3m6!1s0x398f8d8233a3f25b:0xbc9063120c115ed8!8m2!3d25.0167028!4d82.3591479!16s%2Fg%2F11gjhfp0g7!19sChIJW_KjM4KNjzkR2F4RDBJjkLw?authuser=0&hl=en&rclk=1",
        "coordinates": {
            "latitude": 25.016702799999997,
            "longitude": 82.3591479
        }
    },
    {
        "name": "Tarapur Masjid",
        "main_category": "Mosque",
        "address": "CPGV+86R Tarapur Masjid, Lalganj Teghra English, Bihar 854117",
        "detailed_address": {
            "ward": null,
            "street": "CPGV+86R",
            "city": "Lalganj Teghra English",
            "postal_code": null,
            "state": "Bihar",
            "country_code": "IN"
        },
        "images": [
            {
                "about": "All",
                "link": "https://streetviewpixels-pa.googleapis.com/v1/thumbnail?panoid=9sG2cIarG9_RlxheJewqug&cb_client=maps_sv.tactile.gps&w=224&h=298&yaw=325.04593&pitch=0&thumbfov=100"
            },
            {
                "about": "Street View & 360deg",
                "link": "https://streetviewpixels-pa.googleapis.com/v1/thumbnail?panoid=9sG2cIarG9_RlxheJewqug&cb_client=maps_sv.tactile.gps&w=224&h=298&yaw=325.04593&pitch=0&thumbfov=100"
            },
            {
                "about": "Videos",
                "link": "https://lh5.googleusercontent.com/p/AF1QipOxqBe_BkGnLW178OhOxLQ9BnopFFdbD2_y8lp-=w224-h398-k-no"
            }
        ],
        "link": "https://www.google.com/maps/place/Tarapur+Masjid/data=!4m7!3m6!1s0x39faba5bf2934f8f:0xb8f686380b50a00c!8m2!3d25.425875!4d87.7430219!16s%2Fg%2F11hbn32kpr!19sChIJj0-T8lu6-jkRDKBQCziG9rg?authuser=0&hl=en&rclk=1",
        "coordinates": {
            "latitude": 25.425874999999998,
            "longitude": 87.7430219
        }
    },
    {
        "name": "Masjid Jannatul Firdaous",
        "main_category": "Mosque",
        "address": "WP8G+269 Masjid Jannatul Firdaous, Salem Bhadari, Lalganj Ajhara, Uttar Pradesh",
        "detailed_address": {
            "ward": null,
            "street": "WP8G+269, Salem Bhadari",
            "city": "Lalganj Ajhara, Salem Bhadari",
            "postal_code": null,
            "state": "Uttar Pradesh",
            "country_code": "IN"
        },
        "images": [
            {
                "about": "All",
                "link": "https://lh5.googleusercontent.com/p/AF1QipMTEbeoJeL63g9HBV0pF0elbO1geQKgyAfjSZAW=w397-h298-k-no"
            },
            {
                "about": "Videos",
                "link": "https://lh5.googleusercontent.com/p/AF1QipO5fo5K0-KLl9WjMbS2Bw8ghx7ahHdWm0i0mFVn=w224-h497-k-no"
            }
        ],
        "link": "https://www.google.com/maps/place/Masjid+Jannatul+Firdaous/data=!4m7!3m6!1s0x399aef04247b49a1:0xc36ff38faa89aaa0!8m2!3d25.915035!4d81.7256095!16s%2Fg%2F11my7d2_80!19sChIJoUl7JATvmjkRoKqJqo_zb8M?authuser=0&hl=en&rclk=1",
        "coordinates": {
            "latitude": 25.915035,
            "longitude": 81.72560949999999
        }
    },
    {
        "name": "Batraul masjid",
        "main_category": "Mosque",
        "address": "V57M+7G3 Batraul masjid, Sonhani - Bhagwanpur Rd, Lalganj, Asadnagar Batraul, Bihar 844121",
        "detailed_address": {
            "ward": null,
            "street": "V57M+7G3, Sonhani - Bhagwanpur Rd",
            "city": "Lalganj, Asadnagar Batraul",
            "postal_code": "844121",
            "state": "Bihar",
            "country_code": "IN"
        },
        "images": [
            {
                "about": "All",
                "link": "https://lh5.googleusercontent.com/p/AF1QipNuymOI5mOxlHeRZTiDNWXRrkI5lf0gzPMu0ug=w645-h298-k-no"
            },
            {
                "about": "Latest",
                "link": "https://lh5.googleusercontent.com/p/AF1QipOGZFyxbCVA5aByR1ZGL8prveYMFEjOtsfwtJ0=w645-h298-k-no"
            },
            {
                "about": "Street View & 360deg",
                "link": "https://streetviewpixels-pa.googleapis.com/v1/thumbnail?panoid=3rGOOF2RZN5IqYAjetty7w&cb_client=maps_sv.tactile.gps&w=224&h=298&yaw=33.940468&pitch=0&thumbfov=100"
            }
        ],
        "link": "https://www.google.com/maps/place/Batraul+masjid/data=!4m7!3m6!1s0x39ed45e6c7c50b91:0x778d6225d8738ea8!8m2!3d25.8631469!4d85.183802!16s%2Fg%2F11rcqvr6kp!19sChIJkQvFx-ZF7TkRqI5z2CVijXc?authuser=0&hl=en&rclk=1",
        "coordinates": {
            "latitude": 25.8631469,
            "longitude": 85.183802
        }
    },
    {
        "name": "Gosiya masjid",
        "main_category": "Mosque",
        "address": "J987+QH2 Gosiya masjid, Lalganj, Parsia Mudpeli, Uttar Pradesh 231211",
        "detailed_address": {
            "ward": null,
            "street": "J987+QH2",
            "city": "Lalganj, Parsia Mudpeli",
            "postal_code": "231211",
            "state": "Uttar Pradesh",
            "country_code": "IN"
        },
        "images": [
            {
                "about": "All",
                "link": "https://lh5.googleusercontent.com/p/AF1QipPxdwxpM8g_NrEV8pdMTuv0a6-XJEeLa1rkK_a1=w224-h398-k-no"
            },
            {
                "about": "Videos",
                "link": "https://lh5.googleusercontent.com/p/AF1QipPxdwxpM8g_NrEV8pdMTuv0a6-XJEeLa1rkK_a1=w224-h398-k-no"
            }
        ],
        "link": "https://www.google.com/maps/place/Gosiya+masjid/data=!4m7!3m6!1s0x398f790f3872012f:0xbd6c56183021254d!8m2!3d24.6168796!4d82.3639045!16s%2Fg%2F11k99f7xdk!19sChIJLwFyOA95jzkRTSUhMBhWbL0?authuser=0&hl=en&rclk=1",
        "coordinates": {
            "latitude": 24.616879599999997,
            "longitude": 82.36390449999999
        }
    },
    {
        "name": "Masjid lalganj",
        "main_category": "School",
        "address": "V6CR+852 Masjid lalganj, Unnamed Road, Laxminagar, Deyi Dee Dhaurahara, Uttar Pradesh 230135",
        "detailed_address": {
            "ward": "Laxminagar",
            "street": "V6CR+852, Unnamed Road",
            "city": "Deyi Dee Dhaurahara",
            "postal_code": "230135",
            "state": "Uttar Pradesh",
            "country_code": "IN"
        },
        "images": [
            {
                "about": "All",
                "link": "https://lh5.googleusercontent.com/p/AF1QipOKLhKOg62oND3QnP8jCXJUziA0Lfm2X33dH6NA=w529-h298-k-no"
            },
            {
                "about": "Videos",
                "link": "https://lh5.googleusercontent.com/p/AF1QipOKLhKOg62oND3QnP8jCXJUziA0Lfm2X33dH6NA=w529-h298-k-no"
            }
        ],
        "link": "https://www.google.com/maps/place/Masjid+lalganj/data=!4m7!3m6!1s0x399075c2f5c57155:0x2df28b335c12a204!8m2!3d25.8707573!4d82.2403788!16s%2Fg%2F11hzkml2nt!19sChIJVXHF9cJ1kDkRBKISXDOL8i0?authuser=0&hl=en&rclk=1",
        "coordinates": {
            "latitude": 25.870757299999998,
            "longitude": 82.2403788
        }
    },
    {
        "name": "Jama masjid jm` msjd",
        "main_category": "Mosque",
        "address": "R232+QC4 Jama masjid jm` msjd, Katghar Lalganj, Uttar Pradesh 276202",
        "detailed_address": {
            "ward": null,
            "street": "R232+QC4",
            "city": "Katghar Lalganj",
            "postal_code": "276202",
            "state": "Uttar Pradesh",
            "country_code": "IN"
        },
        "images": [
            {
                "about": "All",
                "link": "https://lh5.googleusercontent.com/p/AF1QipO-fp1C3ik_ifgC5pZNajYFEloGdxkiz2K6WeVX=w224-h407-k-no"
            },
            {
                "about": "Videos",
                "link": "https://lh5.googleusercontent.com/p/AF1QipO-fp1C3ik_ifgC5pZNajYFEloGdxkiz2K6WeVX=w224-h407-k-no"
            }
        ],
        "link": "https://www.google.com/maps/place/Jama+masjid+%D8%AC%D8%A7%D9%85%D8%B9+%D9%85%D8%B3%D8%AC%D8%AF%E2%80%AD/data=!4m7!3m6!1s0x3991c92b80c94a05:0x36b97dd2dc19e9bd!8m2!3d25.8043943!4d83.0010787!16s%2Fg%2F11h07p38kf!19sChIJBUrJgCvJkTkRvekZ3NJ9uTY?authuser=0&hl=en&rclk=1",
        "coordinates": {
            "latitude": 25.8043943,
            "longitude": 83.0010787
        }
    },
    {
        "name": "Sareni Eidgaah Masjid",
        "main_category": "Mosque",
        "address": "5R3F+7MR Sareni Eidgaah Masjid, Lalganj, Uttar Pradesh 229212",
        "detailed_address": {
            "ward": null,
            "street": "5R3F+7MR",
            "city": "Lalganj",
            "postal_code": "229212",
            "state": "Uttar Pradesh",
            "country_code": "IN"
        },
        "images": [
            {
                "about": "All",
                "link": "https://lh5.googleusercontent.com/p/AF1QipNQaadmX_RwZjCwTJfT6F1rlKhwc1Vaoo_BSqMF=w667-h298-k-no"
            }
        ],
        "link": "https://www.google.com/maps/place/Sareni+Eidgaah+Masjid/data=!4m7!3m6!1s0x399b81961b11bc25:0xb23deaf0ec91652e!8m2!3d26.1532405!4d80.8241318!16s%2Fg%2F11v3f_37vg!19sChIJJbwRG5aBmzkRLmWR7PDqPbI?authuser=0&hl=en&rclk=1",
        "coordinates": {
            "latitude": 26.1532405,
            "longitude": 80.82413179999999
        }
    },
    {
        "name": "Muhammadi masjid",
        "main_category": "Mosque",
        "address": "5WMQ+Q3C Muhammadi masjid, Maduri Gaon, lalganj, Mubarakpur, Uttar Pradesh",
        "detailed_address": {
            "ward": null,
            "street": "5WMQ+Q3C, Maduri Gaon, lalganj",
            "city": "Mubarakpur, Maduri",
            "postal_code": null,
            "state": "Uttar Pradesh",
            "country_code": "IN"
        },
        "images": [
            {
                "about": "All",
                "link": "https://lh5.googleusercontent.com/p/AF1QipNbLs1ZUnB_vbfwbI1LfzgUjve6EwNWnDtFTmru=w529-h298-k-no"
            },
            {
                "about": "Street View & 360deg",
                "link": "https://streetviewpixels-pa.googleapis.com/v1/thumbnail?panoid=mjU3BLcdRkDYBrjNZKVLtA&cb_client=maps_sv.tactile.gps&w=224&h=298&yaw=177.82648&pitch=0&thumbfov=100"
            }
        ],
        "link": "https://www.google.com/maps/place/Muhammadi+masjid/data=!4m7!3m6!1s0x399b83c8ef06ab81:0x66bf19ea465ffbdc!8m2!3d26.1844351!4d80.9376452!16s%2Fg%2F11tn3x94xg!19sChIJgasG78iDmzkR3PtfRuoZv2Y?authuser=0&hl=en&rclk=1",
        "coordinates": {
            "latitude": 26.184435099999998,
            "longitude": 80.93764519999999
        }
    },
    {
        "name": "Masjid-E-Fatima",
        "main_category": "Mosque",
        "address": "7W6V+63 Masjid-E-Fatima, Gillation Market Campus, Lalganj, Madhubani, Bihar 847211",
        "detailed_address": {
            "ward": "Gillation Market Campus",
            "street": "7W6V+63",
            "city": "Lalganj, Madhubani",
            "postal_code": null,
            "state": "Bihar",
            "country_code": "IN"
        },
        "images": [
            {
                "about": "All",
                "link": "https://lh5.googleusercontent.com/p/AF1QipN4AMgkjdTACOsMvZPOj0byaf822rQ8txAXIomR=w529-h298-k-no"
            },
            {
                "about": "Street View & 360deg",
                "link": "https://streetviewpixels-pa.googleapis.com/v1/thumbnail?panoid=X8rcOzeEd13pNzQgJFl5Qg&cb_client=maps_sv.tactile.gps&w=224&h=298&yaw=290.68655&pitch=0&thumbfov=100"
            }
        ],
        "link": "https://www.google.com/maps/place/Masjid-E-Fatima/data=!4m7!3m6!1s0x39edcd6845ec2fb3:0x5ecc391587ed3fa6!8m2!3d26.3482196!4d86.0711247!16s%2Fg%2F11sx6x3b_t!19sChIJsy_sRWjN7TkRpj_thxU5zF4?authuser=0&hl=en&rclk=1",
        "coordinates": {
            "latitude": 26.3482196,
            "longitude": 86.0711247
        }
    },
    {
        "name": "Noori Jama Masjid",
        "main_category": "Mosque",
        "address": "Noori Jama Masjid, lalganj raebareli, Vill post Gajpati khera radesh, Sareni, Uttar Pradesh 229212",
        "detailed_address": {
            "ward": null,
            "street": "lalganj raebareli, Vill post Gajpati khera radesh",
            "city": "Sareni, Gachpatikheda",
            "postal_code": "229212",
            "state": "Uttar Pradesh",
            "country_code": "IN"
        },
        "images": [],
        "link": "https://www.google.com/maps/place/Noori+Jama+Masjid/data=!4m7!3m6!1s0x399c7f863c4aa1a5:0x7727ed3533d1dbbb!8m2!3d26.1790501!4d80.7655433!16s%2Fg%2F11sht5qm_t!19sChIJpaFKPIZ_nDkRu9vRMzXtJ3c?authuser=0&hl=en&rclk=1",
        "coordinates": {
            "latitude": 26.179050099999998,
            "longitude": 80.76554329999999
        }
    },
    {
        "name": "Makkah Masjid Katauli Kalan",
        "main_category": "Mosque",
        "address": "QXFX+VX2 Makkah Masjid Katauli Kalan, Narayanpur newada, Lalganj, Uttar Pradesh 276202",
        "detailed_address": {
            "ward": null,
            "street": "QXFX+VX2, Narayanpur newada",
            "city": "Lalganj, Narayanpur Nevada",
            "postal_code": "276202",
            "state": "Uttar Pradesh",
            "country_code": "IN"
        },
        "images": [],
        "link": "https://www.google.com/maps/place/Makkah+Masjid+Katauli+Kalan/data=!4m7!3m6!1s0x3991cf251c23d683:0x3a4cabd7f1bcbaa4!8m2!3d25.7746498!4d82.9998862!16s%2Fg%2F11h00c_ly_!19sChIJg9YjHCXPkTkRpLq88derTDo?authuser=0&hl=en&rclk=1",
        "coordinates": {
            "latitude": 25.7746498,
            "longitude": 82.99988619999999
        }
    },
    {
        "name": "Jama Majid",
        "main_category": "Mosque",
        "address": "CPGR+6PR Jama Majid, Tarapur, Lalganj Teghra English, Bihar 854117",
        "detailed_address": {
            "ward": null,
            "street": "CPGR+6PR",
            "city": "Tarapur, Lalganj Teghra English",
            "postal_code": null,
            "state": "Bihar",
            "country_code": "IN"
        },
        "images": [],
        "link": "https://www.google.com/maps/place/Jama+Majid/data=!4m7!3m6!1s0x39fabb105de09c71:0x92aec4d80d56aa5e!8m2!3d25.4256162!4d87.7417601!16s%2Fg%2F11ff1yvn9x!19sChIJcZzgXRC7-jkRXqpWDdjErpI?authuser=0&hl=en&rclk=1",
        "coordinates": {
            "latitude": 25.4256162,
            "longitude": 87.7417601
        }
    },
    {
        "name": "Nori Jama Masjid.Sari Ghat, Lalganj",
        "main_category": "Mosque",
        "address": "MR59+3HQ Nori Jama Masjid.Sari Ghat, Lalganj, Lalganj, Uttar Pradesh 272171",
        "detailed_address": {
            "ward": null,
            "street": "MR59+3HQ",
            "city": "Lalganj",
            "postal_code": "272171",
            "state": "Uttar Pradesh",
            "country_code": "IN"
        },
        "images": [],
        "link": "https://www.google.com/maps/place/Nori+Jama+Masjid.Sari+Ghat,+Lalganj/data=!4m7!3m6!1s0x3990ddf0509ea507:0x3aa79212933f4f31!8m2!3d26.6577232!4d82.8189746!16s%2Fg%2F11kj0zhdgx!19sChIJB6WeUPDdkDkRMU8_kxKSpzo?authuser=0&hl=en&rclk=1",
        "coordinates": {
            "latitude": 26.6577232,
            "longitude": 82.81897459999999
        }
    },
    {
        "name": "Masjid Faizan, Bairidih, Lalganj",
        "main_category": "Mosque",
        "address": "Q2JF+G5M Masjid Faizan, Bairidih, Lalganj, Bairdih, Uttar Pradesh 276202",
        "detailed_address": {
            "ward": null,
            "street": "Q2JF+G5M",
            "city": "Bairdih",
            "postal_code": "276202",
            "state": "Uttar Pradesh",
            "country_code": "IN"
        },
        "images": [
            {
                "about": "All",
                "link": "https://lh5.googleusercontent.com/p/AF1QipPi8NFjwnpV9vfgzK_l0uFLDpXzS0iAv6993xIR=w397-h298-k-no"
            }
        ],
        "link": "https://www.google.com/maps/place/Masjid+Faizan,+Bairidih,+Lalganj/data=!4m7!3m6!1s0x3991c96ae4c00ab9:0x6269510e4e88853!8m2!3d25.7816283!4d83.02273!16s%2Fg%2F11jybh20d4!19sChIJuQrA5GrJkTkRU4jo5BCVJgY?authuser=0&hl=en&rclk=1",
        "coordinates": {
            "latitude": 25.781628299999998,
            "longitude": 83.02273
        }
    },
    {
        "name": "sunni masjid khanyara lalganj",
        "main_category": "Housing society",
        "address": "R287+GGW sunni masjid khanyara lalganj, Manuwa, Uttar Pradesh 276202",
        "detailed_address": {
            "ward": null,
            "street": "R287+GGW",
            "city": "Manuwa",
            "postal_code": "276202",
            "state": "Uttar Pradesh",
            "country_code": "IN"
        },
        "images": [],
        "link": "https://www.google.com/maps/place/sunni+masjid+khanyara+lalganj/data=!4m7!3m6!1s0x3991c9b0040058cb:0x879e2fe6efb63937!8m2!3d25.8163528!4d83.0138437!16s%2Fg%2F11vhrns_6z!19sChIJy1gABLDJkTkRNzm27-Yvnoc?authuser=0&hl=en&rclk=1",
        "coordinates": {
            "latitude": 25.816352799999997,
            "longitude": 83.0138437
        }
    },
    {
        "name": "Masjid bakkas nagar",
        "main_category": "Place of worship",
        "address": "RX3Q+8JQ Masjid bakkas nagar, Lalganj, Katghar Lalganj, Uttar Pradesh 276202",
        "detailed_address": {
            "ward": null,
            "street": "RX3Q+8JQ",
            "city": "Lalganj, Katghar Lalganj",
            "postal_code": "276202",
            "state": "Uttar Pradesh",
            "country_code": "IN"
        },
        "images": [],
        "link": "https://www.google.com/maps/place/Masjid+bakkas+nagar/data=!4m7!3m6!1s0x3991cb895a9852ef:0x7265d44f9deb9fe8!8m2!3d25.8033311!4d82.9891204!16s%2Fg%2F11t7_9_8g6!19sChIJ71KYWonLkTkR6J_rnU_UZXI?authuser=0&hl=en&rclk=1",
        "coordinates": {
            "latitude": 25.803331099999998,
            "longitude": 82.98912039999999
        }
    },
    {
        "name": "Sarai ghat Jama Masjid",
        "main_category": "Mosque",
        "address": "MR6C+HJF Sarai ghat Jama Masjid, Lalganj, Uttar Pradesh 272171",
        "detailed_address": {
            "ward": null,
            "street": "MR6C+HJF",
            "city": "Lalganj",
            "postal_code": "272171",
            "state": "Uttar Pradesh",
            "country_code": "IN"
        },
        "images": [],
        "link": "https://www.google.com/maps/place/Sarai+ghat+Jama+Masjid/data=!4m7!3m6!1s0x3990dfe2700d8a03:0x8f456699ba498173!8m2!3d26.6614468!4d82.8212188!16s%2Fg%2F11sb0fk04f!19sChIJA4oNcOLfkDkRc4FJuplmRY8?authuser=0&hl=en&rclk=1",
        "coordinates": {
            "latitude": 26.6614468,
            "longitude": 82.8212188
        }
    },
    {
        "name": "puraanii msjid",
        "main_category": "Mosque",
        "address": "V599+56V puraanii msjid, Lalganj Vaishali Rd, Lalganj, Bihar 844121",
        "detailed_address": {
            "ward": null,
            "street": "V599+56V, Lalganj Vaishali Rd",
            "city": "Lalganj",
            "postal_code": "844121",
            "state": "Bihar",
            "country_code": "IN"
        },
        "images": [
            {
                "about": "All",
                "link": "https://streetviewpixels-pa.googleapis.com/v1/thumbnail?panoid=tze9rxU8eAXA5XRwJJ0E1Q&cb_client=maps_sv.tactile.gps&w=224&h=298&yaw=286.73022&pitch=0&thumbfov=100"
            },
            {
                "about": "Street View & 360deg",
                "link": "https://streetviewpixels-pa.googleapis.com/v1/thumbnail?panoid=tze9rxU8eAXA5XRwJJ0E1Q&cb_client=maps_sv.tactile.gps&w=224&h=298&yaw=286.73022&pitch=0&thumbfov=100"
            }
        ],
        "link": "https://www.google.com/maps/place/%E0%A4%AA%E0%A5%81%E0%A4%B0%E0%A4%BE%E0%A4%A8%E0%A5%80+%E0%A4%AE%E0%A4%B8%E0%A5%8D%E0%A4%9C%E0%A4%BF%E0%A4%A6/data=!4m7!3m6!1s0x39ed470f42cc0831:0xddf36969fe023ca8!8m2!3d25.8679995!4d85.1680427!16s%2Fg%2F11q1vv3bdg!19sChIJMQjMQg9H7TkRqDwC_mlp890?authuser=0&hl=en&rclk=1",
        "coordinates": {
            "latitude": 25.8679995,
            "longitude": 85.1680427
        }
    },
    {
        "name": "Abbas Ali Mosque (Masjid)",
        "main_category": "Mosque",
        "address": "VJJV+RVX Abbas Ali Mosque (Masjid), Jalesharganj Road, Lalganj Ajhara, Shitalmau, Uttar Pradesh 230132",
        "detailed_address": {
            "ward": null,
            "street": "VJJV+RVX, Jalesharganj Road",
            "city": "Lalganj Ajhara, Shitalmau",
            "postal_code": "230132",
            "state": "Uttar Pradesh",
            "country_code": "IN"
        },
        "images": [],
        "link": "https://www.google.com/maps/place/Abbas+Ali+Mosque+%28Masjid%29/data=!4m7!3m6!1s0x399ae7c8627e8751:0xb4460b796a6dffc0!8m2!3d25.8821199!4d81.6447202!16s%2Fg%2F11l23qs_vb!19sChIJUYd-YsjnmjkRwP9tankLRrQ?authuser=0&hl=en&rclk=1",
        "coordinates": {
            "latitude": 25.8821199,
            "longitude": 81.6447202
        }
    },
    {
        "name": "Madni masjid",
        "main_category": "Mosque",
        "address": "Madni masjid, madni market, NH 28, Lalganj, Sarai Maroof, Uttar Pradesh 276202",
        "detailed_address": {
            "ward": null,
            "street": "madni market, NH 28",
            "city": "Lalganj, Sarai Maroof",
            "postal_code": "276202",
            "state": "Uttar Pradesh",
            "country_code": "IN"
        },
        "images": [
            {
                "about": "All",
                "link": "https://lh5.googleusercontent.com/p/AF1QipPjILAnUgiPGu-W9oXkLK-zacke51kh9ZT7AUtA=w224-h298-k-no"
            }
        ],
        "link": "https://www.google.com/maps/place/Madni+masjid/data=!4m7!3m6!1s0x3991c927dfb6032f:0x325a89c276b286bb!8m2!3d25.7838613!4d82.9955798!16s%2Fg%2F11r2r1zc2p!19sChIJLwO23yfJkTkRu4aydsKJWjI?authuser=0&hl=en&rclk=1",
        "coordinates": {
            "latitude": 25.783861299999998,
            "longitude": 82.9955798
        }
    },
    {
        "name": "Noori Masjid",
        "main_category": "Mosque",
        "address": "V57C+V4V Noori Masjid, Lalganj, Bihar 844121",
        "detailed_address": {
            "ward": null,
            "street": "V57C+V4V",
            "city": "Lalganj",
            "postal_code": "844121",
            "state": "Bihar",
            "country_code": "IN"
        },
        "images": [],
        "link": "https://www.google.com/maps/place/Noori+Masjid/data=!4m7!3m6!1s0x39ed452479650981:0xb8f46594fd3c2626!8m2!3d25.8647316!4d85.1702823!16s%2Fg%2F11l3583vjw!19sChIJgQlleSRF7TkRJiY8_ZRl9Lg?authuser=0&hl=en&rclk=1",
        "coordinates": {
            "latitude": 25.8647316,
            "longitude": 85.1702823
        }
    },
    {
        "name": "Masjid Al-Qadir",
        "main_category": "Mosque",
        "address": "QXQW+26C Masjid Al-Qadir, Lalganj, Uttar Pradesh 276202",
        "detailed_address": {
            "ward": null,
            "street": "QXQW+26C",
            "city": "Lalganj",
            "postal_code": null,
            "state": "Uttar Pradesh",
            "country_code": "IN"
        },
        "images": [],
        "link": "https://www.google.com/maps/place/Masjid+Al-Qadir/data=!4m7!3m6!1s0x3991c952ff613ffb:0xd8300fc955ca895c!8m2!3d25.7875587!4d82.9955133!16s%2Fg%2F11t0svtyc3!19sChIJ-z9h_1LJkTkRXInKVckPMNg?authuser=0&hl=en&rclk=1",
        "coordinates": {
            "latitude": 25.787558699999998,
            "longitude": 82.9955133
        }
    },
    {
        "name": "Bagha Masjid",
        "main_category": "Mosque",
        "address": "7X27+W3W Bagha Masjid, Badh Samaila, Lalganj, Bihar 847337",
        "detailed_address": {
            "ward": "Badh Samaila",
            "street": "7X27+W3W",
            "city": "Lalganj",
            "postal_code": "847337",
            "state": "Bihar",
            "country_code": "IN"
        },
        "images": [
            {
                "about": "All",
                "link": "https://streetviewpixels-pa.googleapis.com/v1/thumbnail?panoid=1Ja0XruG53FyD6ewIqROzg&cb_client=maps_sv.tactile.gps&w=224&h=298&yaw=267.7511&pitch=0&thumbfov=100"
            },
            {
                "about": "Street View & 360deg",
                "link": "https://streetviewpixels-pa.googleapis.com/v1/thumbnail?panoid=1Ja0XruG53FyD6ewIqROzg&cb_client=maps_sv.tactile.gps&w=224&h=298&yaw=267.7511&pitch=0&thumbfov=100"
            }
        ],
        "link": "https://www.google.com/maps/place/Bagha+Masjid/data=!4m7!3m6!1s0x39edc934e6c83b6f:0xf156930145947431!8m2!3d26.2523739!4d85.9627014!16s%2Fg%2F11rvg57yz3!19sChIJbzvI5jTJ7TkRMXSURQGTVvE?authuser=0&hl=en&rclk=1",
        "coordinates": {
            "latitude": 26.2523739,
            "longitude": 85.9627014
        }
    },
    {
        "name": "Noor Masjid (nuur msjid)",
        "main_category": "Mosque",
        "address": "QXGV+J89 Noor Masjid (nuur msjid), Shekhupur, Chhawni, Lalganj, Uttar Pradesh",
        "detailed_address": {
            "ward": "Chhawni",
            "street": "QXGV+J89, Shekhupur",
            "city": "Lalganj, Shekhupur",
            "postal_code": null,
            "state": "Uttar Pradesh",
            "country_code": "IN"
        },
        "images": [
            {
                "about": "All",
                "link": "https://lh5.googleusercontent.com/p/AF1QipPPYN06cnAUHIOvZvlle9HGoA9qAQ9BzY5jcjT7=w224-h298-k-no"
            },
            {
                "about": "Dome",
                "link": "https://lh5.googleusercontent.com/p/AF1QipO6XZc-UTEWwU40eOWQBp4kwv3ye3hg1Uquan2G=w224-h377-k-no"
            },
            {
                "about": "Street View & 360deg",
                "link": "https://streetviewpixels-pa.googleapis.com/v1/thumbnail?panoid=G_jgcQyOyy0lWtr3EWY1jg&cb_client=maps_sv.tactile.gps&w=224&h=298&yaw=243.95056&pitch=0&thumbfov=100"
            }
        ],
        "link": "https://www.google.com/maps/place/Noor+Masjid+%28%E0%A4%A8%E0%A5%82%E0%A4%B0+%E0%A4%AE%E0%A4%B8%E0%A5%8D%E0%A4%9C%E0%A4%BF%E0%A4%A6%29/data=!4m7!3m6!1s0x3991cfd8c42c741b:0x23f761f295af403e!8m2!3d25.776531!4d82.9933536!16s%2Fg%2F11v0c8gn_r!19sChIJG3QsxNjPkTkRPkCvlfJh9yM?authuser=0&hl=en&rclk=1",
        "coordinates": {
            "latitude": 25.776531,
            "longitude": 82.99335359999999
        }
    },
    {
        "name": "Masjid Mehnajpur",
        "main_category": "Mosque",
        "address": "M4G8+5XM Masjid Mehnajpur, Rd, Lalganj, Tarwa, Mehnajpur, Chakia Kasrawal, Uttar Pradesh 276203",
        "detailed_address": {
            "ward": "Lalganj, Tarwa",
            "street": "M4G8+5XM, Rd",
            "city": "Mehnajpur, Chakia Kasrawal",
            "postal_code": "276203",
            "state": "Uttar Pradesh",
            "country_code": "IN"
        },
        "images": [
            {
                "about": "All",
                "link": "https://streetviewpixels-pa.googleapis.com/v1/thumbnail?panoid=PxXnBV4xswKQXDZAsSwZ3A&cb_client=maps_sv.tactile.gps&w=224&h=298&yaw=48.80582&pitch=0&thumbfov=100"
            },
            {
                "about": "Street View & 360deg",
                "link": "https://streetviewpixels-pa.googleapis.com/v1/thumbnail?panoid=PxXnBV4xswKQXDZAsSwZ3A&cb_client=maps_sv.tactile.gps&w=224&h=298&yaw=48.80582&pitch=0&thumbfov=100"
            }
        ],
        "link": "https://www.google.com/maps/place/Masjid+Mehnajpur/data=!4m7!3m6!1s0x3991db67d6fbf943:0x75a2fb18c73dcc83!8m2!3d25.6751104!4d83.1177018!16s%2Fg%2F11qbsb8dly!19sChIJQ_n71mfbkTkRg8w9xxj7onU?authuser=0&hl=en&rclk=1",
        "coordinates": {
            "latitude": 25.675110399999998,
            "longitude": 83.11770179999999
        }
    },
    {
        "name": "Vishunpur masjid",
        "main_category": "Mosque",
        "address": "W5XP+FCC Vishunpur masjid, Lalganj-Jatkauli Ghat Rd, Madarna, Bihar 844113",
        "detailed_address": {
            "ward": null,
            "street": "W5XP+FCC, Lalganj-Jatkauli Ghat Rd",
            "city": "Madarna",
            "postal_code": "844113",
            "state": "Bihar",
            "country_code": "IN"
        },
        "images": [
            {
                "about": "All",
                "link": "https://streetviewpixels-pa.googleapis.com/v1/thumbnail?panoid=WX97yE6wpXD9qX8cO1KjDQ&cb_client=maps_sv.tactile.gps&w=224&h=298&yaw=203.49644&pitch=0&thumbfov=100"
            },
            {
                "about": "Street View & 360deg",
                "link": "https://streetviewpixels-pa.googleapis.com/v1/thumbnail?panoid=WX97yE6wpXD9qX8cO1KjDQ&cb_client=maps_sv.tactile.gps&w=224&h=298&yaw=203.49644&pitch=0&thumbfov=100"
            }
        ],
        "link": "https://www.google.com/maps/place/Vishunpur+masjid/data=!4m7!3m6!1s0x39ed47c3ac75f477:0x56dc32b6531c52e6!8m2!3d25.9486876!4d85.1860156!16s%2Fg%2F11hdy1zqd5!19sChIJd_R1rMNH7TkR5lIcU7Yy3FY?authuser=0&hl=en&rclk=1",
        "coordinates": {
            "latitude": 25.9486876,
            "longitude": 85.18601559999999
        }
    }
]