[
    {
        "name": "Ali Ibn Abu Talib Mosque",
        "main_category": "Mosque",
        "address": "Ali Ibn Abu Talib Mosque, 12, Jagat Narayan Rd, Golaganj, Maulviganj, Wazirganj, Lucknow, Uttar Pradesh 226018",
        "detailed_address": {
            "ward": "Golaganj, Maulviganj, Wazirganj",
            "street": "12, Jagat Narayan Rd",
            "city": "Lucknow",
            "postal_code": "226018",
            "state": "Uttar Pradesh",
            "country_code": "IN"
        },
        "images": [
            {
                "about": "All",
                "link": "https://lh5.googleusercontent.com/p/AF1QipOUR-mYB-z641wxkwGq9Eqj0x8LHtDiEVE8EMbd=w397-h298-k-no"
            },
            {
                "about": "Street View & 360deg",
                "link": "https://streetviewpixels-pa.googleapis.com/v1/thumbnail?panoid=QDA3YqoR6jpxCTb93i9GYg&cb_client=maps_sv.tactile.gps&w=224&h=298&yaw=217.6346&pitch=0&thumbfov=100"
            }
        ],
        "link": "https://www.google.com/maps/place/Ali+Ibn+Abu+Talib+Mosque/data=!4m7!3m6!1s0x399bfdbe94e8f05f:0xfd729b353206a549!8m2!3d26.8538515!4d80.9249232!16s%2Fg%2F1tj50_q9!19sChIJX_DolL79mzkRSaUGMjWbcv0?authuser=0&hl=en&rclk=1",
        "coordinates": {
            "latitude": 26.853851499999998,
            "longitude": 80.9249232
        }
    },
    {
        "name": "Wali Masjid",
        "main_category": "Mosque",
        "address": "Wali Masjid, Lakshman Parsad Road, Lakshmanprasad Srivastava Rd, Wazirganj, Lucknow, Uttar Pradesh 226018",
        "detailed_address": {
            "ward": "Wazirganj",
            "street": "Lakshman Parsad Road, Lakshmanprasad Srivastava Rd",
            "city": "Lucknow",
            "postal_code": "226018",
            "state": "Uttar Pradesh",
            "country_code": "IN"
        },
        "images": [
            {
                "about": "All",
                "link": "https://lh5.googleusercontent.com/p/AF1QipPXrWvkX0bmvdJS4969p-zP7erjs1oZU5kp6TdS=w224-h298-k-no"
            },
            {
                "about": "Dome",
                "link": "https://lh5.googleusercontent.com/p/AF1QipPXrWvkX0bmvdJS4969p-zP7erjs1oZU5kp6TdS=w224-h298-k-no"
            },
            {
                "about": "By owner",
                "link": "https://lh5.googleusercontent.com/p/AF1QipOkUIvy1XIiYt3n0tB1sQTa8g6l5l1F4Xrs4d_f=w298-h298-k-no"
            },
            {
                "about": "Street View & 360deg",
                "link": "https://streetviewpixels-pa.googleapis.com/v1/thumbnail?panoid=3iFvqqUcH8lbmGT8dAQOJA&cb_client=maps_sv.tactile.gps&w=224&h=298&yaw=246.4084&pitch=0&thumbfov=100"
            }
        ],
        "link": "https://www.google.com/maps/place/Wali+Masjid/data=!4m7!3m6!1s0x399bfd4548485579:0x8b1238f619049c26!8m2!3d26.8562866!4d80.9206659!16s%2Fg%2F11g0km15k_!19sChIJeVVISEX9mzkRJpwEGfY4Eos?authuser=0&hl=en&rclk=1",
        "coordinates": {
            "latitude": 26.856286599999997,
            "longitude": 80.9206659
        }
    },
    {
        "name": "Mohammadia Mosque ( Masjid )",
        "main_category": "Mosque",
        "address": "VVJP+FWC Mohammadia Mosque ( Masjid ), c/o Hafiz Maqsood Alam , Misri Ki Bagia, Jal Nigam Rd, Near, Balaganj, Lucknow, Uttar Pradesh 226003",
        "detailed_address": {
            "ward": "Near, Balaganj",
            "street": "VVJP+FWC, c/o Hafiz Maqsood Alam , Misri Ki Bagia, Jal Nigam Rd",
            "city": "Lucknow",
            "postal_code": "226003",
            "state": "Uttar Pradesh",
            "country_code": "IN"
        },
        "images": [
            {
                "about": "All",
                "link": "https://lh5.googleusercontent.com/p/AF1QipP_SM4BjVpLoLkzQfkX5rabVSO4fgFZVZtfkG9D=w308-h298-k-no"
            },
            {
                "about": "Dome",
                "link": "https://lh5.googleusercontent.com/p/AF1QipPM_dMR-Imalk6ZUtniSrlJSaK1PPj9-ON0Gn1i=w224-h298-k-no"
            },
            {
                "about": "Videos",
                "link": "https://lh5.googleusercontent.com/p/AF1QipMqEQWkQxY9jqzItjUvEaV3I2hIIou8ZEBTlRVU=w224-h389-k-no"
            },
            {
                "about": "Street View & 360deg",
                "link": "https://streetviewpixels-pa.googleapis.com/v1/thumbnail?panoid=YQkcUj_kIAsX6zBH-PiuKg&cb_client=maps_sv.tactile.gps&w=224&h=298&yaw=263.08273&pitch=0&thumbfov=100"
            }
        ],
        "link": "https://www.google.com/maps/place/Mohammadia+Mosque+%28+Masjid+%29/data=!4m7!3m6!1s0x399955f788d64d87:0xcca3b54e9151c0e5!8m2!3d26.8811921!4d80.8872501!16s%2Fg%2F11b7q6m4p4!19sChIJh03WiPdVmTkR5cBRkU61o8w?authuser=0&hl=en&rclk=1",
        "coordinates": {
            "latitude": 26.8811921,
            "longitude": 80.8872501
        }
    },
    {
        "name": "Lal Masjid",
        "main_category": "Mosque",
        "address": "Lal Masjid, Golaganj, 157, Jagat Narayan Rd, Wazirganj, Lucknow, Uttar Pradesh 226018",
        "detailed_address": {
            "ward": "Maulviganj, Wazirganj",
            "street": "Golaganj, 157, Jagat Narayan Rd",
            "city": "Lucknow",
            "postal_code": "226018",
            "state": "Uttar Pradesh",
            "country_code": "IN"
        },
        "images": [
            {
                "about": "All",
                "link": "https://lh5.googleusercontent.com/p/AF1QipOfSISOsZf2u-vfuucJMXDHSm2tENSERGVj8VBd=w224-h497-k-no"
            },
            {
                "about": "Street View & 360deg",
                "link": "https://streetviewpixels-pa.googleapis.com/v1/thumbnail?panoid=D-4ulmsNAsMXJFgRLtjjpA&cb_client=maps_sv.tactile.gps&w=224&h=298&yaw=18.694412&pitch=0&thumbfov=100"
            }
        ],
        "link": "https://www.google.com/maps/place/Lal+Masjid/data=!4m7!3m6!1s0x399bfdbf0d64e989:0x42250b173f7e097e!8m2!3d26.8548608!4d80.9224767!16s%2Fg%2F12hk5jnws!19sChIJielkDb_9mzkRfgl-PxcLJUI?authuser=0&hl=en&rclk=1",
        "coordinates": {
            "latitude": 26.854860799999997,
            "longitude": 80.92247669999999
        }
    },
    {
        "name": "Jama Masjid",
        "main_category": "Mosque",
        "address": "VW48+CPM Jama Masjid, Mashakganj, Wazirganj, Lucknow, Uttar Pradesh 226018",
        "detailed_address": {
            "ward": "Bagh Sher Jung, Wazirganj",
            "street": "VW48+CPM, Mashakganj",
            "city": "Lucknow",
            "postal_code": "226018",
            "state": "Uttar Pradesh",
            "country_code": "IN"
        },
        "images": [
            {
                "about": "All",
                "link": "https://lh5.googleusercontent.com/p/AF1QipM0Dpje20Fv_BMlyYU0lFp7nHT9GiOTyKw8P_9f=w224-h298-k-no"
            },
            {
                "about": "Videos",
                "link": "https://lh5.googleusercontent.com/p/AF1QipNxoh54AGkYnMTMMDMNYD0YqN7EWL9B7don_BEN=w224-h398-k-no"
            }
        ],
        "link": "https://www.google.com/maps/place/Jama+Masjid/data=!4m7!3m6!1s0x399bfdc1c17737ed:0x13f00a3c6bffdc76!8m2!3d26.8560821!4d80.9167941!16s%2Fg%2F12qh8p0zp!19sChIJ7Td3wcH9mzkRdtz_azwK8BM?authuser=0&hl=en&rclk=1",
        "coordinates": {
            "latitude": 26.8560821,
            "longitude": 80.91679409999999
        }
    },
    {
        "name": "Aminabad Masjid ( Shia)",
        "main_category": "Mosque",
        "address": "RWXG+X3J Aminabad Masjid ( Shia), Aminabada, ICICI Bank, Aminabad, Lucknow, Uttar Pradesh 226018",
        "detailed_address": {
            "ward": "Kesar Bagh, Maulviganj, Wazirganj",
            "street": "RWXG+X3J, Aminabada, ICICI Bank, Aminabad",
            "city": "Lucknow",
            "postal_code": "226018",
            "state": "Uttar Pradesh",
            "country_code": "IN"
        },
        "images": [
            {
                "about": "All",
                "link": "https://lh5.googleusercontent.com/p/AF1QipMoTIAtvDMhdd4m4Yei-WW1LcslBcFnR-2PsEx3=w528-h298-k-no"
            },
            {
                "about": "Dome",
                "link": "https://lh5.googleusercontent.com/p/AF1QipPHbmnK01V8oTmfqxY6muvyw5b4I_1rmG2n-zfz=w397-h298-k-no"
            },
            {
                "about": "Videos",
                "link": "https://lh5.googleusercontent.com/p/AF1QipM5DU0x4-I2FgeCH1fyBvaUWUbKHQ2aW5LikPeG=w529-h298-k-no"
            },
            {
                "about": "Street View & 360deg",
                "link": "https://streetviewpixels-pa.googleapis.com/v1/thumbnail?panoid=RVX6ElPh7e6hyLyp6qjq5g&cb_client=maps_sv.tactile.gps&w=224&h=298&yaw=281.93387&pitch=0&thumbfov=100"
            }
        ],
        "link": "https://www.google.com/maps/place/Aminabad+Masjid+%28+Shia%29/data=!4m7!3m6!1s0x399bfdb90b47471b:0xa06b676c170a7ae8!8m2!3d26.8499575!4d80.9251511!16s%2Fg%2F1w15xvmy!19sChIJG0dHC7n9mzkR6HoKF2xna6A?authuser=0&hl=en&rclk=1",
        "coordinates": {
            "latitude": 26.8499575,
            "longitude": 80.9251511
        }
    },
    {
        "name": "Masjid Anwar aakhoon zadah (Mosque)",
        "main_category": "Mosque",
        "address": "VW2F+GJ9 Masjid Anwar aakhoon zadah (Mosque), Haider Mirza Rd, Maulviganj, Wazirganj, Lucknow, Uttar Pradesh 226018",
        "detailed_address": {
            "ward": "Maulviganj, Wazirganj",
            "street": "VW2F+GJ9, Haider Mirza Rd",
            "city": "Lucknow",
            "postal_code": "226018",
            "state": "Uttar Pradesh",
            "country_code": "IN"
        },
        "images": [
            {
                "about": "All",
                "link": "https://lh5.googleusercontent.com/p/AF1QipNx8Fy89XrC9vcqO7s6SIIEcjielUQSeuKKXNed=w224-h398-k-no"
            },
            {
                "about": "Dome",
                "link": "https://lh5.googleusercontent.com/p/AF1QipNGG0CI8rcOG5r6HGrqcSp0_JdMjaLsKguyMcGs=w224-h470-k-no"
            },
            {
                "about": "Videos",
                "link": "https://lh5.googleusercontent.com/p/AF1QipNGG0CI8rcOG5r6HGrqcSp0_JdMjaLsKguyMcGs=w224-h470-k-no"
            }
        ],
        "link": "https://www.google.com/maps/place/Masjid+Anwar+aakhoon+zadah+%28Mosque%29/data=!4m7!3m6!1s0x399bfd2fd3e3a293:0xe80bed67d0734788!8m2!3d26.8512793!4d80.9240993!16s%2Fg%2F11ghwq1yph!19sChIJk6Lj0y_9mzkRiEdz0GftC-g?authuser=0&hl=en&rclk=1",
        "coordinates": {
            "latitude": 26.851279299999998,
            "longitude": 80.9240993
        }
    },
    {
        "name": "Masjid Khwas",
        "main_category": "Mosque",
        "address": "RWXC+PWR Masjid Khwas, Gangaprasad Marg, Maulviganj, Aminabad, Lucknow, Uttar Pradesh 226018",
        "detailed_address": {
            "ward": "Maulviganj, Aminabad",
            "street": "RWXC+PWR, Gangaprasad Marg",
            "city": "Lucknow",
            "postal_code": "226018",
            "state": "Uttar Pradesh",
            "country_code": "IN"
        },
        "images": [
            {
                "about": "All",
                "link": "https://lh5.googleusercontent.com/p/AF1QipMyxnSlO3g557q9K3XKCeb1OJZbupVeJXnFZT6B=w529-h298-k-no"
            },
            {
                "about": "Street View & 360deg",
                "link": "https://streetviewpixels-pa.googleapis.com/v1/thumbnail?panoid=qtaT0Bn71NU0Xbo-5xPEmg&cb_client=maps_sv.tactile.gps&w=224&h=298&yaw=16.363888&pitch=0&thumbfov=100"
            },
            {
                "about": "Videos",
                "link": "https://lh5.googleusercontent.com/p/AF1QipN1982c-tTy-eaBvqKrGilt8RWSGoseFmqc2-uA=w224-h398-k-no"
            }
        ],
        "link": "https://www.google.com/maps/place/Masjid+Khwas/data=!4m7!3m6!1s0x399bfdb8f4ea42e5:0x15b8dd8181d18486!8m2!3d26.84936!4d80.9222552!16s%2Fg%2F1th1b3c9!19sChIJ5ULq9Lj9mzkRhoTRgYHduBU?authuser=0&hl=en&rclk=1",
        "coordinates": {
            "latitude": 26.849359999999997,
            "longitude": 80.9222552
        }
    },
    {
        "name": "Masjid Kareem Shah Chikmandi",
        "main_category": "Mosque",
        "address": "Masjid Kareem Shah Chikmandi, 163,Mosque Abdul Kareem Shah, Chikmandi, Maulviganj, Wazirganj, Lucknow, Uttar Pradesh 226018",
        "detailed_address": {
            "ward": "Maulviganj, Wazirganj",
            "street": "163,Mosque Abdul Kareem Shah, Chikmandi",
            "city": "Lucknow",
            "postal_code": "226018",
            "state": "Uttar Pradesh",
            "country_code": "IN"
        },
        "images": [
            {
                "about": "All",
                "link": "https://lh5.googleusercontent.com/p/AF1QipPc7lZN7F8P7OD0ArM0VLrpjLZoT-ML5DAcmGY3=w662-h298-k-no"
            }
        ],
        "link": "https://www.google.com/maps/place/Masjid+Kareem+Shah+Chikmandi/data=!4m7!3m6!1s0x399bfd5045c4b217:0x5423bb86189eeb83!8m2!3d26.8524282!4d80.9216607!16s%2Fg%2F11h1_0m4yd!19sChIJF7LERVD9mzkRg-ueGIa7I1Q?authuser=0&hl=en&rclk=1",
        "coordinates": {
            "latitude": 26.8524282,
            "longitude": 80.92166069999999
        }
    },
    {
        "name": "JAMA MASJID WAZIRGAJ",
        "main_category": "Mosque",
        "address": "Q6XQ+R3V JAMA MASJID WAZIRGAJ, Bhareti, Bihar 805131",
        "detailed_address": {
            "ward": null,
            "street": "Q6XQ+R3V",
            "city": "Bhareti",
            "postal_code": "805131",
            "state": "Bihar",
            "country_code": "IN"
        },
        "images": [
            {
                "about": "All",
                "link": "https://lh5.googleusercontent.com/p/AF1QipNtITu0GI_5N-52iU8GZ3X4stGp98_fwU7Fl8RJ=w224-h485-k-no"
            },
            {
                "about": "Videos",
                "link": "https://lh5.googleusercontent.com/p/AF1QipNKpYpDvxn4uka2UcSj5DsRJakNlBqvc15cZM2K=w224-h398-k-no"
            }
        ],
        "link": "https://www.google.com/maps/place/JAMA+MASJID+WAZIRGAJ/data=!4m7!3m6!1s0x39f3205c71783895:0x871118a7c8fdc473!8m2!3d24.7996041!4d85.237679!16s%2Fg%2F11gfh7k7z7!19sChIJlTh4cVwg8zkRc8T9yKcYEYc?authuser=0&hl=en&rclk=1",
        "coordinates": {
            "latitude": 24.7996041,
            "longitude": 85.237679
        }
    },
    {
        "name": "Mohammadi masjid",
        "main_category": "Mosque",
        "address": "VV7J+CWC Mohammadi masjid, Mozzam Nagar, Wazirbagh Mohallah, Lucknow, Uttar Pradesh 226003",
        "detailed_address": {
            "ward": "Mozzam Nagar, Wazirbagh Mohallah",
            "street": "VV7J+CWC",
            "city": "Lucknow",
            "postal_code": "226003",
            "state": "Uttar Pradesh",
            "country_code": "IN"
        },
        "images": [
            {
                "about": "All",
                "link": "https://lh5.googleusercontent.com/p/AF1QipNUS6cGPnCjRIOW9lAzxHM2MfNEZTNIEQ7A0KBA=w224-h398-k-no"
            },
            {
                "about": "Dome",
                "link": "https://lh5.googleusercontent.com/p/AF1QipNUS6cGPnCjRIOW9lAzxHM2MfNEZTNIEQ7A0KBA=w224-h398-k-no"
            }
        ],
        "link": "https://www.google.com/maps/place/Mohammadi+masjid/data=!4m7!3m6!1s0x399bfe112c5b8a7f:0xd83aeee47998b25f!8m2!3d26.8635582!4d80.8822542!16s%2Fg%2F11gdlxt876!19sChIJf4pbLBH-mzkRX7KYeeTuOtg?authuser=0&hl=en&rclk=1",
        "coordinates": {
            "latitude": 26.8635582,
            "longitude": 80.88225419999999
        }
    },
    {
        "name": "Hari Masjid daliganj",
        "main_category": "Mosque",
        "address": "Hari Masjid daliganj, 498/55, Acharya Narendradev Marg, Kutubpur, Hasanganj, Lucknow, Uttar Pradesh 226007",
        "detailed_address": {
            "ward": "Kutubpur, Hasanganj",
            "street": "498/55, Acharya Narendradev Marg",
            "city": "Lucknow",
            "postal_code": "226007",
            "state": "Uttar Pradesh",
            "country_code": "IN"
        },
        "images": [
            {
                "about": "All",
                "link": "https://lh5.googleusercontent.com/p/AF1QipPL_fy5X3QGn1TmfK180bj1pAgezK11dK5FU7MZ=w224-h398-k-no"
            },
            {
                "about": "Street View & 360deg",
                "link": "https://streetviewpixels-pa.googleapis.com/v1/thumbnail?panoid=hxB3bXAig2bntfVtd2uCqQ&cb_client=maps_sv.tactile.gps&w=224&h=298&yaw=172.43227&pitch=0&thumbfov=100"
            },
            {
                "about": "Videos",
                "link": "https://lh5.googleusercontent.com/p/AF1QipNvF5o9vCqTStiEBv3R5HdXKWiNSt_7NYfwckta=w224-h407-k-no"
            }
        ],
        "link": "https://www.google.com/maps/place/Hari+Masjid+daliganj/data=!4m7!3m6!1s0x399bfd12b2fc89a5:0x91ffa4f5385a5b88!8m2!3d26.8717292!4d80.9305203!16s%2Fg%2F11kk1vh413!19sChIJpYn8shL9mzkRiFtaOPWk_5E?authuser=0&hl=en&rclk=1",
        "coordinates": {
            "latitude": 26.871729199999997,
            "longitude": 80.9305203
        }
    },
    {
        "name": "Khajoor Wali Masjid",
        "main_category": "Mosque",
        "address": "VW3F+W7P Khajoor Wali Masjid, Jagat Narayan Rd, Maulviganj, Wazirganj, Lucknow, Uttar Pradesh 226018",
        "detailed_address": {
            "ward": "Maulviganj, Wazirganj",
            "street": "VW3F+W7P, Jagat Narayan Rd",
            "city": "Lucknow",
            "postal_code": "226018",
            "state": "Uttar Pradesh",
            "country_code": "IN"
        },
        "images": [
            {
                "about": "All",
                "link": "https://streetviewpixels-pa.googleapis.com/v1/thumbnail?panoid=Ga9fehITLF982Ja7e9JX3g&cb_client=maps_sv.tactile.gps&w=224&h=298&yaw=256.06857&pitch=0&thumbfov=100"
            },
            {
                "about": "Street View & 360deg",
                "link": "https://streetviewpixels-pa.googleapis.com/v1/thumbnail?panoid=Ga9fehITLF982Ja7e9JX3g&cb_client=maps_sv.tactile.gps&w=224&h=298&yaw=256.06857&pitch=0&thumbfov=100"
            }
        ],
        "link": "https://www.google.com/maps/place/Khajoor+Wali+Masjid/data=!4m7!3m6!1s0x399bfdbf00a58e55:0xd0889d6de492cb02!8m2!3d26.8548444!4d80.9232147!16s%2Fg%2F11h0dqb2b!19sChIJVY6lAL_9mzkRAsuS5G2diNA?authuser=0&hl=en&rclk=1",
        "coordinates": {
            "latitude": 26.854844399999998,
            "longitude": 80.9232147
        }
    },
    {
        "name": "Khajoor Wali Masjid",
        "main_category": "Mosque",
        "address": "VV7P+4FV Khajoor Wali Masjid, Wazirbagh Mohallah, Lucknow, Uttar Pradesh 226003",
        "detailed_address": {
            "ward": "Wazirbagh Mohallah",
            "street": "VV7P+4FV",
            "city": "Lucknow",
            "postal_code": "226003",
            "state": "Uttar Pradesh",
            "country_code": "IN"
        },
        "images": [
            {
                "about": "All",
                "link": "https://lh5.googleusercontent.com/p/AF1QipMqLJCC6w5RCGJVJHq0ZISyB7nfBecD9UwjSiKX=w224-h398-k-no"
            },
            {
                "about": "Street View & 360deg",
                "link": "https://streetviewpixels-pa.googleapis.com/v1/thumbnail?panoid=WHmSGIihfmbA07XWDEvBcg&cb_client=maps_sv.tactile.gps&w=224&h=298&yaw=58.48857&pitch=0&thumbfov=100"
            },
            {
                "about": "Videos",
                "link": "https://lh5.googleusercontent.com/p/AF1QipO64rqMY3eoYU1qdiBuz-pJMff13A3-LXLG-S2Z=w224-h398-k-no"
            }
        ],
        "link": "https://www.google.com/maps/place/Khajoor+Wali+Masjid/data=!4m7!3m6!1s0x399bfe11bfffffff:0x300032b8633e325f!8m2!3d26.8628652!4d80.886172!16s%2Fg%2F11btwtcr0t!19sChIJ____vxH-mzkRXzI-Y7gyADA?authuser=0&hl=en&rclk=1",
        "coordinates": {
            "latitude": 26.862865199999998,
            "longitude": 80.886172
        }
    },
    {
        "name": "Mosque",
        "main_category": "Mosque",
        "address": "VW2G+M5W Mosque, Gwynne Rd, Maulviganj, Aminabad, Lucknow, Uttar Pradesh 226018",
        "detailed_address": {
            "ward": "Maulviganj, Aminabad",
            "street": "VW2G+M5W, Gwynne Rd",
            "city": "Lucknow",
            "postal_code": "226018",
            "state": "Uttar Pradesh",
            "country_code": "IN"
        },
        "images": [
            {
                "about": "All",
                "link": "https://lh5.googleusercontent.com/p/AF1QipMbqAJBBQaYQ6yLf3dtuop5TqGIiE8U0i5llSF2=w224-h298-k-no"
            },
            {
                "about": "Street View & 360deg",
                "link": "https://streetviewpixels-pa.googleapis.com/v1/thumbnail?panoid=LEKAY88dgTkbQAswc5apUw&cb_client=maps_sv.tactile.gps&w=224&h=298&yaw=315.39417&pitch=0&thumbfov=100"
            }
        ],
        "link": "https://www.google.com/maps/place/Mosque/data=!4m7!3m6!1s0x399bfdb94e59b071:0x2dfcd7462bbd4b13!8m2!3d26.8517255!4d80.9254535!16s%2Fg%2F12hkhbp_l!19sChIJcbBZTrn9mzkRE0u9K0bX_C0?authuser=0&hl=en&rclk=1",
        "coordinates": {
            "latitude": 26.851725499999997,
            "longitude": 80.9254535
        }
    },
    {
        "name": "Masjid-e-Aisha",
        "main_category": "Mosque",
        "address": "Masjid-e-Aisha, 12, Jagat Narayan Rd, Golaganj, Maulviganj, Wazirganj, Lucknow, Uttar Pradesh 226018",
        "detailed_address": {
            "ward": "Golaganj, Maulviganj, Wazirganj",
            "street": "12, Jagat Narayan Rd",
            "city": "Lucknow",
            "postal_code": "226018",
            "state": "Uttar Pradesh",
            "country_code": "IN"
        },
        "images": [
            {
                "about": "All",
                "link": "https://lh5.googleusercontent.com/p/AF1QipPfdoExnUvSEvfdce982U9PPXnckB1prJKSfEmW=w224-h298-k-no"
            },
            {
                "about": "Street View & 360deg",
                "link": "https://streetviewpixels-pa.googleapis.com/v1/thumbnail?panoid=Bk1EnOLn12Y6H9FP_vpivQ&cb_client=maps_sv.tactile.gps&w=224&h=298&yaw=241.18501&pitch=0&thumbfov=100"
            }
        ],
        "link": "https://www.google.com/maps/place/Masjid-e-Aisha/data=!4m7!3m6!1s0x399bfdbea766d413:0xc4f96598c408bc26!8m2!3d26.8532749!4d80.9263041!16s%2Fg%2F11fx9mb0x_!19sChIJE9Rmp779mzkRJrwIxJhl-cQ?authuser=0&hl=en&rclk=1",
        "coordinates": {
            "latitude": 26.8532749,
            "longitude": 80.9263041
        }
    },
    {
        "name": "Chilwar Wali Masjid (Masjid E Muavia)",
        "main_category": "Mosque",
        "address": "VV4Q+F5C Chilwar Wali Masjid (Masjid E Muavia), Saadatganj, Lucknow, Uttar Pradesh 226003",
        "detailed_address": {
            "ward": "Saadatganj",
            "street": "VV4Q+F5C",
            "city": "Lucknow",
            "postal_code": "226003",
            "state": "Uttar Pradesh",
            "country_code": "IN"
        },
        "images": [
            {
                "about": "All",
                "link": "https://streetviewpixels-pa.googleapis.com/v1/thumbnail?panoid=dEvzxHGm8CdgfqBGiiT4bQ&cb_client=maps_sv.tactile.gps&w=224&h=298&yaw=251.19658&pitch=0&thumbfov=100"
            },
            {
                "about": "Street View & 360deg",
                "link": "https://streetviewpixels-pa.googleapis.com/v1/thumbnail?panoid=dEvzxHGm8CdgfqBGiiT4bQ&cb_client=maps_sv.tactile.gps&w=224&h=298&yaw=251.19658&pitch=0&thumbfov=100"
            }
        ],
        "link": "https://www.google.com/maps/place/Chilwar+Wali+Masjid+%28Masjid+E+Muavia%29/data=!4m7!3m6!1s0x399bfe0d573178bb:0x7ac4e6d8d483c376!8m2!3d26.856182!4d80.8878766!16s%2Fg%2F11c5_c19_s!19sChIJu3gxVw3-mzkRdsOD1NjmxHo?authuser=0&hl=en&rclk=1",
        "coordinates": {
            "latitude": 26.856182,
            "longitude": 80.8878766
        }
    },
    {
        "name": "Tazikhana Masjid",
        "main_category": "Mosque",
        "address": "Tazikhana Masjid, tazikhana, 161/94, raod, Patthar Wali Gali, Astabal Charbagh, Mashak Ganj, Wazirganj, Lucknow, Uttar Pradesh 226018",
        "detailed_address": {
            "ward": "Patthar Wali Gali, Astabal Charbagh, Mashak Ganj, Wazirganj",
            "street": "tazikhana, 161/94, raod",
            "city": "Lucknow",
            "postal_code": "226018",
            "state": "Uttar Pradesh",
            "country_code": "IN"
        },
        "images": [
            {
                "about": "All",
                "link": "https://lh5.googleusercontent.com/p/AF1QipMLNBI_KeA1uPR8ilJaZGRu_0s82BwAFgRP5joq=w529-h298-k-no"
            }
        ],
        "link": "https://www.google.com/maps/place/Tazikhana+Masjid/data=!4m7!3m6!1s0x399bfd98b044fcfb:0xf7d68a2f08f184b3!8m2!3d26.8530363!4d80.9176886!16s%2Fg%2F11flbq022h!19sChIJ-_xEsJj9mzkRs4TxCC-K1vc?authuser=0&hl=en&rclk=1",
        "coordinates": {
            "latitude": 26.8530363,
            "longitude": 80.91768859999999
        }
    },
    {
        "name": "Masjid jamiatul Quraish",
        "main_category": "Mosque",
        "address": "VW2C+FP2 Masjid jamiatul Quraish, Chickmandi, Maulviganj, Wazirganj, Lucknow, Uttar Pradesh 226018",
        "detailed_address": {
            "ward": "Maulviganj, Wazirganj",
            "street": "VW2C+FP2, Chickmandi",
            "city": "Lucknow",
            "postal_code": "226018",
            "state": "Uttar Pradesh",
            "country_code": "IN"
        },
        "images": [
            {
                "about": "All",
                "link": "https://lh5.googleusercontent.com/p/AF1QipM7HuKY8czbsM9EjeBYzEL2HTBHNSxG4I2J59Ot=w224-h398-k-no"
            },
            {
                "about": "Dome",
                "link": "https://lh5.googleusercontent.com/p/AF1QipMf-tuBJgYvzTLupIg9dgZXrgjUOEfZPM7yrrsD=w224-h398-k-no"
            },
            {
                "about": "Videos",
                "link": "https://lh5.googleusercontent.com/p/AF1QipMnxtyDlW1hg2b9xqY6d6GBYCoc12XAXE61pu4m=w224-h389-k-no"
            }
        ],
        "link": "https://www.google.com/maps/place/Masjid+jamiatul+Quraish/data=!4m7!3m6!1s0x399bfd32d9414c5f:0xe05019756cade05c!8m2!3d26.8511411!4d80.9217726!16s%2Fg%2F11jcml8m5p!19sChIJX0xB2TL9mzkRXOCtbHUZUOA?authuser=0&hl=en&rclk=1",
        "coordinates": {
            "latitude": 26.8511411,
            "longitude": 80.9217726
        }
    },
    {
        "name": "Gumbadi masjid",
        "main_category": "Mosque",
        "address": "VW3C+PX5 Gumbadi masjid, Maulviganj, Wazirganj, Lucknow, Uttar Pradesh 226018",
        "detailed_address": {
            "ward": "Maulviganj, Wazirganj",
            "street": "VW3C+PX5",
            "city": "Lucknow",
            "postal_code": "226018",
            "state": "Uttar Pradesh",
            "country_code": "IN"
        },
        "images": [
            {
                "about": "All",
                "link": "https://lh5.googleusercontent.com/p/AF1QipM56x8mUk-mFzP7wymwryrPZO00dXLdgZlzprZX=w440-h298-k-no"
            },
            {
                "about": "Street View & 360deg",
                "link": "https://streetviewpixels-pa.googleapis.com/v1/thumbnail?panoid=Vt5SfkUfSKECMUOKm-pNuw&cb_client=maps_sv.tactile.gps&w=224&h=298&yaw=92.87256&pitch=0&thumbfov=100"
            }
        ],
        "link": "https://www.google.com/maps/place/Gumbadi+masjid/data=!4m7!3m6!1s0x399bfdc8672dfeb1:0x43df5ad0f3ce6d6f!8m2!3d26.8542532!4d80.922473!16s%2Fg%2F11h77wwj9j!19sChIJsf4tZ8j9mzkRb23O89Ba30M?authuser=0&hl=en&rclk=1",
        "coordinates": {
            "latitude": 26.8542532,
            "longitude": 80.922473
        }
    },
    {
        "name": "Ruhani Jama Masjid",
        "main_category": "Mosque",
        "address": "W4PF+98W Ruhani Jama Masjid, Wazir Ganj, Uttar Pradesh 271129",
        "detailed_address": {
            "ward": null,
            "street": "W4PF+98W",
            "city": "Wazir Ganj",
            "postal_code": "271129",
            "state": "Uttar Pradesh",
            "country_code": "IN"
        },
        "images": [
            {
                "about": "All",
                "link": "https://streetviewpixels-pa.googleapis.com/v1/thumbnail?panoid=yCz_j0Wz7UvuVpexwW75Zg&cb_client=maps_sv.tactile.gps&w=224&h=298&yaw=111.13234&pitch=0&thumbfov=100"
            },
            {
                "about": "Street View & 360deg",
                "link": "https://streetviewpixels-pa.googleapis.com/v1/thumbnail?panoid=yCz_j0Wz7UvuVpexwW75Zg&cb_client=maps_sv.tactile.gps&w=224&h=298&yaw=111.13234&pitch=0&thumbfov=100"
            }
        ],
        "link": "https://www.google.com/maps/place/Ruhani+Jama+Masjid/data=!4m7!3m6!1s0x399a021c1d91a185:0xab0e8d4d0776df02!8m2!3d26.9359827!4d82.1233277!16s%2Fg%2F11c2j90pwv!19sChIJhaGRHRwCmjkRAt92B02NDqs?authuser=0&hl=en&rclk=1",
        "coordinates": {
            "latitude": 26.9359827,
            "longitude": 82.12332769999999
        }
    },
    {
        "name": "Mulsare Mosque",
        "main_category": "Mosque",
        "address": "VW3G+24M Mulsare Mosque, Gwynne Rd, Maulviganj, Aminabad, Lucknow, Uttar Pradesh 226018",
        "detailed_address": {
            "ward": "Maulviganj, Aminabad",
            "street": "VW3G+24M, Gwynne Rd",
            "city": "Lucknow",
            "postal_code": "226018",
            "state": "Uttar Pradesh",
            "country_code": "IN"
        },
        "images": [
            {
                "about": "All",
                "link": "https://streetviewpixels-pa.googleapis.com/v1/thumbnail?panoid=KlmGuskQ-KivjsRtRNAKuA&cb_client=maps_sv.tactile.gps&w=224&h=298&yaw=271.76276&pitch=0&thumbfov=100"
            },
            {
                "about": "Street View & 360deg",
                "link": "https://streetviewpixels-pa.googleapis.com/v1/thumbnail?panoid=KlmGuskQ-KivjsRtRNAKuA&cb_client=maps_sv.tactile.gps&w=224&h=298&yaw=271.76276&pitch=0&thumbfov=100"
            }
        ],
        "link": "https://www.google.com/maps/place/Mulsare+Mosque/data=!4m7!3m6!1s0x399bfdbeb157ff89:0x1f426f02149f60c2!8m2!3d26.8525921!4d80.9252847!16s%2Fg%2F12hnqgw9g!19sChIJif9Xsb79mzkRwmCfFAJvQh8?authuser=0&hl=en&rclk=1",
        "coordinates": {
            "latitude": 26.8525921,
            "longitude": 80.92528469999999
        }
    },
    {
        "name": "Hari Masjid",
        "main_category": "Mosque",
        "address": "VW3G+358 Hari Masjid, Barudkhana, Lal Masjid, Golaganj, Lucknow, Uttar Pradesh 226018",
        "detailed_address": {
            "ward": "Maulviganj, Wazirganj",
            "street": "VW3G+358, Barudkhana, Lal Masjid, Golaganj",
            "city": "Lucknow",
            "postal_code": "226018",
            "state": "Uttar Pradesh",
            "country_code": "IN"
        },
        "images": [
            {
                "about": "All",
                "link": "https://streetviewpixels-pa.googleapis.com/v1/thumbnail?panoid=KlmGuskQ-KivjsRtRNAKuA&cb_client=maps_sv.tactile.gps&w=224&h=298&yaw=38.851788&pitch=0&thumbfov=100"
            },
            {
                "about": "Street View & 360deg",
                "link": "https://streetviewpixels-pa.googleapis.com/v1/thumbnail?panoid=KlmGuskQ-KivjsRtRNAKuA&cb_client=maps_sv.tactile.gps&w=224&h=298&yaw=38.851788&pitch=0&thumbfov=100"
            }
        ],
        "link": "https://www.google.com/maps/place/Hari+Masjid/data=!4m7!3m6!1s0x399bfdbeb1747c7f:0x85f6080f29dcd3b3!8m2!3d26.8526743!4d80.9254578!16s%2Fg%2F1tftcq_m!19sChIJf3x0sb79mzkRs9PcKQ8I9oU?authuser=0&hl=en&rclk=1",
        "coordinates": {
            "latitude": 26.8526743,
            "longitude": 80.92545779999999
        }
    },
    {
        "name": "Bilal Masjid",
        "main_category": "Mosque",
        "address": "RWXF+JRQ Bilal Masjid, ICICI Bank, Maulviganj, Aminabad, Lucknow, Uttar Pradesh 226018",
        "detailed_address": {
            "ward": "Maulviganj, Aminabad",
            "street": "RWXF+JRQ ICICI Bank",
            "city": "Lucknow",
            "postal_code": "226018",
            "state": "Uttar Pradesh",
            "country_code": "IN"
        },
        "images": [
            {
                "about": "All",
                "link": "https://lh5.googleusercontent.com/p/AF1QipMTyKGUyeJVLcIdiUFfDvF__LQbIEDTKnQkEJqq=w397-h298-k-no"
            },
            {
                "about": "Dome",
                "link": "https://lh5.googleusercontent.com/p/AF1QipODnwxwXX-AUoL9gNCdC-RmpPx8Q330apw7yF7t=w529-h298-k-no"
            },
            {
                "about": "Street View & 360deg",
                "link": "https://streetviewpixels-pa.googleapis.com/v1/thumbnail?panoid=Odgpg0C2T-h-apBJqCP7BQ&cb_client=maps_sv.tactile.gps&w=224&h=298&yaw=209.16626&pitch=0&thumbfov=100"
            }
        ],
        "link": "https://www.google.com/maps/place/Bilal+Masjid/data=!4m7!3m6!1s0x399bfdb9a119909d:0x95a3320bc40b8a93!8m2!3d26.8490869!4d80.9246161!16s%2Fg%2F1tds535k!19sChIJnZAZobn9mzkRk4oLxAsyo5U?authuser=0&hl=en&rclk=1",
        "coordinates": {
            "latitude": 26.8490869,
            "longitude": 80.9246161
        }
    },
    {
        "name": "Chapakhana Masjid",
        "main_category": "Mosque",
        "address": "VW38+2WF Chapakhana Masjid, Massaganj Dhal, Kundari Rakabganj, Lucknow, Uttar Pradesh 226018",
        "detailed_address": {
            "ward": "Patthar Wali Gali, Astabal Charbagh, Kundari Rakabganj",
            "street": "VW38+2WF, Massaganj Dhal",
            "city": "Lucknow",
            "postal_code": "226018",
            "state": "Uttar Pradesh",
            "country_code": "IN"
        },
        "images": [],
        "link": "https://www.google.com/maps/place/Chapakhana+Masjid/data=!4m7!3m6!1s0x399bfdc13ac8b523:0xedc92cd45f1ddb1e!8m2!3d26.8525547!4d80.9172898!16s%2Fg%2F12hkzlcd1!19sChIJI7XIOsH9mzkRHtsdX9Qsye0?authuser=0&hl=en&rclk=1",
        "coordinates": {
            "latitude": 26.8525547,
            "longitude": 80.91728979999999
        }
    },
    {
        "name": "Jama Masjid",
        "main_category": "Mosque",
        "address": "WCPG+WV5 Jama Masjid, Shahid peer ali khan Rd, Muslim Tola, Nardiganj, Bihar 805109",
        "detailed_address": {
            "ward": "Muslim Tola",
            "street": "WCPG+WV5, Shahid peer ali khan Rd",
            "city": "Nardiganj",
            "postal_code": "805109",
            "state": "Bihar",
            "country_code": "IN"
        },
        "images": [
            {
                "about": "All",
                "link": "https://lh5.googleusercontent.com/p/AF1QipPlJ7kALlYPCHIQzPcwo1p0h7YXQ1--bxBb4KPQ=w527-h298-k-no"
            },
            {
                "about": "Street View & 360deg",
                "link": "https://lh5.googleusercontent.com/p/AF1QipNWqr-fw1_t07x0Eicl5APTcmz5GBSaLOmtHfiT=w224-h298-k-no-pi-10-ya78-ro-0-fo100"
            },
            {
                "about": "Videos",
                "link": "https://lh5.googleusercontent.com/p/AF1QipN8zjWU-WfVfZm1UWNla-VKhHP-KXQaaRbnEVky=w529-h298-k-no"
            }
        ],
        "link": "https://www.google.com/maps/place/Jama+Masjid/data=!4m7!3m6!1s0x39f2e4a588262d97:0xeaaeed1cb6f6c239!8m2!3d24.9372625!4d85.4272344!16s%2Fg%2F11dfgt9_hh!19sChIJly0miKXk8jkROcL2thztruo?authuser=0&hl=en&rclk=1",
        "coordinates": {
            "latitude": 24.9372625,
            "longitude": 85.4272344
        }
    },
    {
        "name": "Masjid QUBA",
        "main_category": "Mosque",
        "address": "VW49+V78 Masjid QUBA, Laxman Prasad Road, Near Buland Bagh, near City Railway Station, 226018",
        "detailed_address": {
            "ward": "Wazirganj",
            "street": "VW49+V78, Laxman Prasad Road, Near Buland Bagh, near City Railway Station",
            "city": "Lucknow",
            "postal_code": "226018",
            "state": "Uttar Pradesh",
            "country_code": "IN"
        },
        "images": [
            {
                "about": "All",
                "link": "https://streetviewpixels-pa.googleapis.com/v1/thumbnail?panoid=m7LuYV4OSJ_E3kZQm-q3rQ&cb_client=maps_sv.tactile.gps&w=224&h=298&yaw=265.88477&pitch=0&thumbfov=100"
            },
            {
                "about": "Street View & 360deg",
                "link": "https://streetviewpixels-pa.googleapis.com/v1/thumbnail?panoid=m7LuYV4OSJ_E3kZQm-q3rQ&cb_client=maps_sv.tactile.gps&w=224&h=298&yaw=265.88477&pitch=0&thumbfov=100"
            }
        ],
        "link": "https://www.google.com/maps/place/Masjid+QUBA/data=!4m7!3m6!1s0x399bfd6d27abeef7:0xe48317a82a2709ba!8m2!3d26.8571619!4d80.9181918!16s%2Fg%2F11h2jv0j99!19sChIJ9-6rJ239mzkRugknKqgXg-Q?authuser=0&hl=en&rclk=1",
        "coordinates": {
            "latitude": 26.857161899999998,
            "longitude": 80.9181918
        }
    },
    {
        "name": "Panditaien Ki Masjid",
        "main_category": "Mosque",
        "address": "Panditaien Ki Masjid, Maulviganj, Wazirganj, Lucknow, Uttar Pradesh 226018",
        "detailed_address": {
            "ward": "Maulviganj, Wazirganj",
            "street": null,
            "city": "Lucknow",
            "postal_code": "226018",
            "state": "Uttar Pradesh",
            "country_code": "IN"
        },
        "images": [
            {
                "about": "All",
                "link": "https://lh5.googleusercontent.com/p/AF1QipMEohOvb3QXtSITlCJP1JtN39EtDnFhIssILOp6=w397-h298-k-no"
            },
            {
                "about": "Dome",
                "link": "https://lh5.googleusercontent.com/p/AF1QipO5tndc0yRovzFvuPFNOet-r6lkr3Cm8zcYHYrI=w397-h298-k-no"
            },
            {
                "about": "Videos",
                "link": "https://lh5.googleusercontent.com/p/AF1QipN88rP43rxxBXWRP6YS9qEMOSsg9GCrFiIliwfU=w529-h298-k-no"
            },
            {
                "about": "By owner",
                "link": "https://lh5.googleusercontent.com/p/AF1QipPitpoWrF0w3uX1Zrf_-H7HKc1HIbL8EVthz0qw=w224-h398-k-no"
            },
            {
                "about": "Street View & 360deg",
                "link": "https://streetviewpixels-pa.googleapis.com/v1/thumbnail?panoid=UoMu2qZOplRM5geVGQTxIA&cb_client=maps_sv.tactile.gps&w=224&h=298&yaw=341.75833&pitch=0&thumbfov=100"
            }
        ],
        "link": "https://www.google.com/maps/place/Panditaien+Ki+Masjid/data=!4m7!3m6!1s0x399bfdb9a6e706fd:0xe8af72f20f23aa51!8m2!3d26.8490308!4d80.9244803!16s%2Fg%2F126472863!19sChIJ_Qbnprn9mzkRUaojD_Jyr-g?authuser=0&hl=en&rclk=1",
        "coordinates": {
            "latitude": 26.849030799999998,
            "longitude": 80.9244803
        }
    },
    {
        "name": "Masjid Raushan Ali",
        "main_category": "Mosque",
        "address": "VW49+G5F Masjid Raushan Ali, Wazirganj, Lucknow, Uttar Pradesh 226018",
        "detailed_address": {
            "ward": "Wazirganj",
            "street": "VW49+G5F",
            "city": "Lucknow",
            "postal_code": "226018",
            "state": "Uttar Pradesh",
            "country_code": "IN"
        },
        "images": [
            {
                "about": "All",
                "link": "https://lh5.googleusercontent.com/p/AF1QipNFBT4H9dkmmmeVpipjMnYA8nTaECe3Zvln3vLI=w397-h298-k-no"
            }
        ],
        "link": "https://www.google.com/maps/place/Masjid+Raushan+Ali/data=!4m7!3m6!1s0x399bfd244d5c283f:0x7f32dd4e70634c8b!8m2!3d26.8563184!4d80.9179149!16s%2Fg%2F11fjy3ltqp!19sChIJPyhcTST9mzkRi0xjcE7dMn8?authuser=0&hl=en&rclk=1",
        "coordinates": {
            "latitude": 26.8563184,
            "longitude": 80.9179149
        }
    },
    {
        "name": "Masjid Momsiri (Shia)",
        "main_category": "Mosque",
        "address": "Masjid Momsiri (Shia), 190/24, Lallumal Mandir Rd, Bagh Sher Jung, Wazirganj, Lucknow, Uttar Pradesh 226018",
        "detailed_address": {
            "ward": "Bagh Sher Jung, Wazirganj",
            "street": "190/24, Lallumal Mandir Rd",
            "city": "Lucknow",
            "postal_code": "226018",
            "state": "Uttar Pradesh",
            "country_code": "IN"
        },
        "images": [],
        "link": "https://www.google.com/maps/place/Masjid+Momsiri+%28Shia%29/data=!4m7!3m6!1s0x399bfdc1bcbe1abb:0x642afe1257e9ad3d!8m2!3d26.855416!4d80.916904!16s%2Fg%2F11gfnff66j!19sChIJuxq-vMH9mzkRPa3pVxL-KmQ?authuser=0&hl=en&rclk=1",
        "coordinates": {
            "latitude": 26.855415999999998,
            "longitude": 80.916904
        }
    },
    {
        "name": "Aatuji Masjid (Shia)",
        "main_category": "Mosque",
        "address": "Aatuji Masjid (Shia), 145/2, Lakshman Prasad Shrivastav Rd, Maulviganj, Wazirganj, Lucknow, Uttar Pradesh 226018",
        "detailed_address": {
            "ward": "Maulviganj, Wazirganj",
            "street": "145/2, Lakshman Prasad Shrivastav Rd",
            "city": "Lucknow",
            "postal_code": "226018",
            "state": "Uttar Pradesh",
            "country_code": "IN"
        },
        "images": [
            {
                "about": "All",
                "link": "https://lh5.googleusercontent.com/p/AF1QipMlJlLEY5XouMD2HsuX_7fsLN2yy9FHvDXUGsoX=w224-h398-k-no"
            },
            {
                "about": "Street View & 360deg",
                "link": "https://streetviewpixels-pa.googleapis.com/v1/thumbnail?panoid=KfoHSzbmFMCiQg1tfq9MrQ&cb_client=maps_sv.tactile.gps&w=224&h=298&yaw=25.278929&pitch=0&thumbfov=100"
            }
        ],
        "link": "https://www.google.com/maps/place/Aatuji+Masjid+%28Shia%29/data=!4m7!3m6!1s0x399bfdbf8c314939:0xf44c8e822571c764!8m2!3d26.8560461!4d80.9213024!16s%2Fg%2F11hcw1tzm3!19sChIJOUkxjL_9mzkRZMdxJYKOTPQ?authuser=0&hl=en&rclk=1",
        "coordinates": {
            "latitude": 26.8560461,
            "longitude": 80.9213024
        }
    },
    {
        "name": "Gazi Munne Khan Masjid",
        "main_category": "Mosque",
        "address": "VW29+6W2 Gazi Munne Khan Masjid, Unnamed Road, Pandey Ganj, Wazirganj, Lucknow, Uttar Pradesh 226018",
        "detailed_address": {
            "ward": "Pandey Ganj, Wazirganj",
            "street": "VW29+6W2, Unnamed Road",
            "city": "Lucknow",
            "postal_code": "226018",
            "state": "Uttar Pradesh",
            "country_code": "IN"
        },
        "images": [
            {
                "about": "All",
                "link": "https://lh5.googleusercontent.com/p/AF1QipPJTDtYnkry5TtVzE3LLFMjw3uittjPpZqlJJAh=w224-h398-k-no"
            },
            {
                "about": "Street View & 360deg",
                "link": "https://streetviewpixels-pa.googleapis.com/v1/thumbnail?panoid=uj2ltA9pNPepB8_Sl73k9A&cb_client=maps_sv.tactile.gps&w=224&h=298&yaw=3.354089&pitch=0&thumbfov=100"
            }
        ],
        "link": "https://www.google.com/maps/place/Gazi+Munne+Khan+Masjid/data=!4m7!3m6!1s0x399bfd8cdf0c43c3:0xca289ad9b6a2e98d!8m2!3d26.8505226!4d80.9197811!16s%2Fg%2F11g2tppjgy!19sChIJw0MM34z9mzkRjemittmaKMo?authuser=0&hl=en&rclk=1",
        "coordinates": {
            "latitude": 26.850522599999998,
            "longitude": 80.9197811
        }
    },
    {
        "name": "Masjid Hakeem Sardar Khan",
        "main_category": "Mosque",
        "address": "193, Masjid Hakeem Sardar Khan, 105, Wazirganj, Lucknow, Uttar Pradesh 226018",
        "detailed_address": {
            "ward": "Wazirganj",
            "street": "193, 105",
            "city": "Lucknow",
            "postal_code": "226018",
            "state": "Uttar Pradesh",
            "country_code": "IN"
        },
        "images": [],
        "link": "https://www.google.com/maps/place/Masjid+Hakeem+Sardar+Khan/data=!4m7!3m6!1s0x399bfdda1689f241:0xecccb9fb0939b2a4!8m2!3d26.8544996!4d80.9196162!16s%2Fg%2F11smgl2p4k!19sChIJQfKJFtr9mzkRpLI5Cfu5zOw?authuser=0&hl=en&rclk=1",
        "coordinates": {
            "latitude": 26.8544996,
            "longitude": 80.9196162
        }
    },
    {
        "name": "Gulsan-e-Warsi madrsha and masjid",
        "main_category": "Mosque",
        "address": "X49V+FM7 Gulsan-e-Warsi madrsha and masjid, Gaura khirideeh, Wazir Ganj, Uttar Pradesh",
        "detailed_address": {
            "ward": null,
            "street": "X49V+FM7, Gaura khirideeh",
            "city": "Wazir Ganj, Khirideeh",
            "postal_code": null,
            "state": "Uttar Pradesh",
            "country_code": "IN"
        },
        "images": [
            {
                "about": "All",
                "link": "https://lh5.googleusercontent.com/p/AF1QipO4uQJClqXe20sqn-hjpbbtrMeh0zLpnXfewZYm=w224-h398-k-no"
            },
            {
                "about": "Videos",
                "link": "https://lh5.googleusercontent.com/p/AF1QipPz8Y48k1WLehyeKlUyQ-Qu6Jl9lekjmtIwWBW3=w224-h398-k-no"
            }
        ],
        "link": "https://www.google.com/maps/place/Gulsan-e-Warsi+madrsha+and+masjid/data=!4m7!3m6!1s0x3999ffbc86a7959f:0xfbd142332fa24200!8m2!3d26.9686597!4d82.1441803!16s%2Fg%2F11q4np1c8d!19sChIJn5Wnhrz_mTkRAEKiLzNC0fs?authuser=0&hl=en&rclk=1",
        "coordinates": {
            "latitude": 26.9686597,
            "longitude": 82.1441803
        }
    },
    {
        "name": "Masjid Do Minara",
        "main_category": "Mosque",
        "address": "Masjid Do Minara, 1228, Qaisar Bagh, Lucknow, Uttar Pradesh 226018",
        "detailed_address": {
            "ward": "Qaisar Bagh",
            "street": "1228",
            "city": "Lucknow",
            "postal_code": "226018",
            "state": "Uttar Pradesh",
            "country_code": "IN"
        },
        "images": [
            {
                "about": "All",
                "link": "https://lh5.googleusercontent.com/p/AF1QipPp20sQy7pchzqF-QHMwVGBKWk8Pe8kzX6_w9XP=w224-h398-k-no"
            },
            {
                "about": "Dome",
                "link": "https://lh5.googleusercontent.com/p/AF1QipOobEa5dyi7NVAAe47_T4oSk8IvKJOyYZso4yxW=w224-h398-k-no"
            },
            {
                "about": "Videos",
                "link": "https://lh5.googleusercontent.com/p/AF1QipPfBauYcXYtbrMVxwiAq2ipulH_BfPKQiv-TTaV=w224-h398-k-no"
            }
        ],
        "link": "https://www.google.com/maps/place/Masjid+Do+Minara/data=!4m7!3m6!1s0x399bfd2dd7f39fd7:0x53971c9b967d040f!8m2!3d26.8632085!4d80.9210591!16s%2Fg%2F11sx21m62h!19sChIJ15_z1y39mzkRDwR9lpscl1M?authuser=0&hl=en&rclk=1",
        "coordinates": {
            "latitude": 26.8632085,
            "longitude": 80.9210591
        }
    },
    {
        "name": "Masjid-e -Alia",
        "main_category": "Mosque",
        "address": "Masjid-e -Alia, 178/102, Haider Mirza Rd, Golaganj, Maulviganj, Wazirganj, Lucknow, Uttar Pradesh 226018",
        "detailed_address": {
            "ward": "Golaganj, Maulviganj, Wazirganj",
            "street": "178/102, Haider Mirza Rd",
            "city": "Lucknow",
            "postal_code": "226018",
            "state": "Uttar Pradesh",
            "country_code": "IN"
        },
        "images": [
            {
                "about": "All",
                "link": "https://streetviewpixels-pa.googleapis.com/v1/thumbnail?panoid=O5JBuUZsx9SdJg94VP5ATw&cb_client=maps_sv.tactile.gps&w=224&h=298&yaw=322.08456&pitch=0&thumbfov=100"
            },
            {
                "about": "Street View & 360deg",
                "link": "https://streetviewpixels-pa.googleapis.com/v1/thumbnail?panoid=O5JBuUZsx9SdJg94VP5ATw&cb_client=maps_sv.tactile.gps&w=224&h=298&yaw=322.08456&pitch=0&thumbfov=100"
            }
        ],
        "link": "https://www.google.com/maps/place/Masjid-e+-Alia/data=!4m7!3m6!1s0x399bfdfeb2c86741:0xe299a1bedc3f44f8!8m2!3d26.8530357!4d80.9248948!16s%2Fg%2F11h711115n!19sChIJQWfIsv79mzkR-EQ_3L6hmeI?authuser=0&hl=en&rclk=1",
        "coordinates": {
            "latitude": 26.8530357,
            "longitude": 80.92489479999999
        }
    },
    {
        "name": "Munkari masjid",
        "main_category": "Mosque",
        "address": "177, Munkari masjid, 98, Gwynne Rd, Maulviganj, Aminabad, Lucknow, Uttar Pradesh 226018",
        "detailed_address": {
            "ward": "Maulviganj, Aminabad",
            "street": "177, 98, Gwynne Rd",
            "city": "Lucknow",
            "postal_code": "226018",
            "state": "Uttar Pradesh",
            "country_code": "IN"
        },
        "images": [
            {
                "about": "All",
                "link": "https://streetviewpixels-pa.googleapis.com/v1/thumbnail?panoid=OrK8yo7JRoTehKph7F5l-w&cb_client=maps_sv.tactile.gps&w=224&h=298&yaw=313.6684&pitch=0&thumbfov=100"
            },
            {
                "about": "Street View & 360deg",
                "link": "https://streetviewpixels-pa.googleapis.com/v1/thumbnail?panoid=OrK8yo7JRoTehKph7F5l-w&cb_client=maps_sv.tactile.gps&w=224&h=298&yaw=313.6684&pitch=0&thumbfov=100"
            }
        ],
        "link": "https://www.google.com/maps/place/Munkari+masjid/data=!4m7!3m6!1s0x399bfdab02d15683:0x6482d6ca255a9969!8m2!3d26.852829!4d80.925286!16s%2Fg%2F11h1k1mf2b!19sChIJg1bRAqv9mzkRaZlaJcrWgmQ?authuser=0&hl=en&rclk=1",
        "coordinates": {
            "latitude": 26.852829,
            "longitude": 80.925286
        }
    },
    {
        "name": "Aisha Masjid",
        "main_category": "Mosque",
        "address": "VRMM+FWH Aisha Masjid, Husainabad, Lucknow, Mahipatmau, Uttar Pradesh 226003",
        "detailed_address": {
            "ward": "Husainabad",
            "street": "VRMM+FWH",
            "city": "Lucknow, Mahipatmau",
            "postal_code": "226003",
            "state": "Uttar Pradesh",
            "country_code": "IN"
        },
        "images": [
            {
                "about": "All",
                "link": "https://streetviewpixels-pa.googleapis.com/v1/thumbnail?panoid=go5UM6-ehGoQwxfyF82NEw&cb_client=maps_sv.tactile.gps&w=224&h=298&yaw=27.778467&pitch=0&thumbfov=100"
            },
            {
                "about": "Street View & 360deg",
                "link": "https://streetviewpixels-pa.googleapis.com/v1/thumbnail?panoid=go5UM6-ehGoQwxfyF82NEw&cb_client=maps_sv.tactile.gps&w=224&h=298&yaw=27.778467&pitch=0&thumbfov=100"
            }
        ],
        "link": "https://www.google.com/maps/place/Aisha+Masjid/data=!4m7!3m6!1s0x399955cbd338be4f:0x8afe73f8ca70e8b2!8m2!3d26.8836936!4d80.8348539!16s%2Fg%2F11qgyd1w_g!19sChIJT74408tVmTkRsuhwyvhz_oo?authuser=0&hl=en&rclk=1",
        "coordinates": {
            "latitude": 26.883693599999997,
            "longitude": 80.8348539
        }
    },
    {
        "name": "Chauari masjid",
        "main_category": "Mosque",
        "address": "HXGJ+3F6 Chauari masjid, Wazirganj, Chauari, Bihar 805131",
        "detailed_address": {
            "ward": null,
            "street": "HXGJ+3F6",
            "city": "Wazirganj, Chauari",
            "postal_code": "805131",
            "state": "Bihar",
            "country_code": "IN"
        },
        "images": [],
        "link": "https://www.google.com/maps/place/Chauari+masjid/data=!4m7!3m6!1s0x39f333ccb47965c5:0x7e0cd11aa04edb59!8m2!3d24.574848!4d84.980392!16s%2Fg%2F11y1lspjqp!19sChIJxWV5tMwz8zkRWdtOoBrRDH4?authuser=0&hl=en&rclk=1",
        "coordinates": {
            "latitude": 24.574848,
            "longitude": 84.980392
        }
    },
    {
        "name": "Badi Masjid",
        "main_category": "Mosque",
        "address": "X459+RF5 Badi Masjid, Wazir Ganj, Uttar Pradesh 271124",
        "detailed_address": {
            "ward": null,
            "street": "X459+RF5",
            "city": "Wazir Ganj",
            "postal_code": null,
            "state": "Uttar Pradesh",
            "country_code": "IN"
        },
        "images": [
            {
                "about": "All",
                "link": "https://streetviewpixels-pa.googleapis.com/v1/thumbnail?panoid=kFiozw0hlqs9a9IOQgh1wQ&cb_client=maps_sv.tactile.gps&w=224&h=298&yaw=244.2354&pitch=0&thumbfov=100"
            },
            {
                "about": "Street View & 360deg",
                "link": "https://streetviewpixels-pa.googleapis.com/v1/thumbnail?panoid=kFiozw0hlqs9a9IOQgh1wQ&cb_client=maps_sv.tactile.gps&w=224&h=298&yaw=244.2354&pitch=0&thumbfov=100"
            }
        ],
        "link": "https://www.google.com/maps/place/Badi+Masjid/data=!4m7!3m6!1s0x3999f9c2c2e3590d:0x4bace1090bac5bb3!8m2!3d26.9595199!4d82.1187393!16s%2Fg%2F11gsbcg4ss!19sChIJDVnjwsL5mTkRs1usCwnhrEs?authuser=0&hl=en&rclk=1",
        "coordinates": {
            "latitude": 26.9595199,
            "longitude": 82.1187393
        }
    },
    {
        "name": "Masjid Noor Muhammad (Ahate Wali)",
        "main_category": "Mosque",
        "address": "93, Masjid Noor Muhammad (Ahate Wali), 1, Wazirganj, Lucknow, Uttar Pradesh 226018",
        "detailed_address": {
            "ward": "Wazirganj",
            "street": "93, 1",
            "city": "Lucknow",
            "postal_code": "226018",
            "state": "Uttar Pradesh",
            "country_code": "IN"
        },
        "images": [],
        "link": "https://www.google.com/maps/place/Masjid+Noor+Muhammad+%28Ahate+Wali%29/data=!4m7!3m6!1s0x399bfd6bcf19f343:0x202507fcd83abb7a!8m2!3d26.8555634!4d80.9187295!16s%2Fg%2F11sghxtp93!19sChIJQ_MZz2v9mzkRers62PwHJSA?authuser=0&hl=en&rclk=1",
        "coordinates": {
            "latitude": 26.855563399999998,
            "longitude": 80.9187295
        }
    },
    {
        "name": "Masjid Ateeqiya",
        "main_category": "Mosque",
        "address": "VW4C+4F2 Masjid Ateeqiya, Badrinath Road, near Barood Khana, Golaganj, Lucknow, Uttar Pradesh 226018",
        "detailed_address": {
            "ward": "Golaganj, Maulviganj, Wazirganj",
            "street": "VW4C+4F2, Badrinath Road, near Barood Khana",
            "city": "Lucknow",
            "postal_code": "226018",
            "state": "Uttar Pradesh",
            "country_code": "IN"
        },
        "images": [
            {
                "about": "All",
                "link": "https://streetviewpixels-pa.googleapis.com/v1/thumbnail?panoid=CZLBecMh6CPeVZCgdlpwpw&cb_client=maps_sv.tactile.gps&w=224&h=298&yaw=278.74976&pitch=0&thumbfov=100"
            },
            {
                "about": "Street View & 360deg",
                "link": "https://streetviewpixels-pa.googleapis.com/v1/thumbnail?panoid=CZLBecMh6CPeVZCgdlpwpw&cb_client=maps_sv.tactile.gps&w=224&h=298&yaw=278.74976&pitch=0&thumbfov=100"
            }
        ],
        "link": "https://www.google.com/maps/place/Masjid+Ateeqiya/data=!4m7!3m6!1s0x399bfddd9343f041:0x8825e0970330f0e6!8m2!3d26.8552722!4d80.9211281!16s%2Fg%2F11fgm2q9f3!19sChIJQfBDk939mzkR5vAwA5fgJYg?authuser=0&hl=en&rclk=1",
        "coordinates": {
            "latitude": 26.855272199999998,
            "longitude": 80.92112809999999
        }
    },
    {
        "name": "Husaini Mosque",
        "main_category": "Mosque",
        "address": "Husaini Mosque, 46, Husanabad Rd\nMusahabganj, Husainabad Trust Rd, Musahabganj, Musahibganj, Daulatganj, Lucknow, Uttar Pradesh 226003",
        "detailed_address": {
            "ward": "Musahabganj, Musahibganj, Daulatganj",
            "street": "46, Husanabad Rd\nMusahabganj, Husainabad Trust Rd",
            "city": "Lucknow",
            "postal_code": "226003",
            "state": "Uttar Pradesh",
            "country_code": "IN"
        },
        "images": [
            {
                "about": "All",
                "link": "https://streetviewpixels-pa.googleapis.com/v1/thumbnail?panoid=d8F3VDTBibCIAChN6rAfrw&cb_client=maps_sv.tactile.gps&w=224&h=298&yaw=271.79047&pitch=0&thumbfov=100"
            },
            {
                "about": "Street View & 360deg",
                "link": "https://streetviewpixels-pa.googleapis.com/v1/thumbnail?panoid=d8F3VDTBibCIAChN6rAfrw&cb_client=maps_sv.tactile.gps&w=224&h=298&yaw=271.79047&pitch=0&thumbfov=100"
            }
        ],
        "link": "https://www.google.com/maps/place/Husaini+Mosque/data=!4m7!3m6!1s0x399bfe010b5f3459:0x482fa39d8c130d9b!8m2!3d26.8761509!4d80.8945669!16s%2Fg%2F11c5szyw2t!19sChIJWTRfCwH-mzkRmw0TjJ2jL0g?authuser=0&hl=en&rclk=1",
        "coordinates": {
            "latitude": 26.8761509,
            "longitude": 80.8945669
        }
    },
    {
        "name": "Dhaniya Mahyri Masjid",
        "main_category": "Mosque",
        "address": "RWXC+XP2 Dhaniya Mahyri Masjid, Maulviganj, Wazirganj, Lucknow, Uttar Pradesh 226018",
        "detailed_address": {
            "ward": "Maulviganj, Wazirganj",
            "street": "RWXC+XP2",
            "city": "Lucknow",
            "postal_code": "226018",
            "state": "Uttar Pradesh",
            "country_code": "IN"
        },
        "images": [
            {
                "about": "All",
                "link": "https://streetviewpixels-pa.googleapis.com/v1/thumbnail?panoid=S2z171x5B81IcBc-UiUm4Q&cb_client=maps_sv.tactile.gps&w=224&h=298&yaw=350.79645&pitch=0&thumbfov=100"
            },
            {
                "about": "Street View & 360deg",
                "link": "https://streetviewpixels-pa.googleapis.com/v1/thumbnail?panoid=S2z171x5B81IcBc-UiUm4Q&cb_client=maps_sv.tactile.gps&w=224&h=298&yaw=350.79645&pitch=0&thumbfov=100"
            }
        ],
        "link": "https://www.google.com/maps/place/Dhaniya+Mahyri+Masjid/data=!4m7!3m6!1s0x399bfd00f83aca77:0x5d8875c820b385c5!8m2!3d26.8498807!4d80.9217736!16s%2Fg%2F11hssxj1fx!19sChIJd8o6-AD9mzkRxYWzIMh1iF0?authuser=0&hl=en&rclk=1",
        "coordinates": {
            "latitude": 26.8498807,
            "longitude": 80.9217736
        }
    },
    {
        "name": "Masjid Padayan",
        "main_category": "Mosque",
        "address": "RWXF+HRH Masjid Padayan, Book Market Rd, Maulviganj, Aminabad, Lucknow, Uttar Pradesh 226018",
        "detailed_address": {
            "ward": "Maulviganj, Aminabad",
            "street": "RWXF+HRH, Book Market Rd",
            "city": "Lucknow",
            "postal_code": "226018",
            "state": "Uttar Pradesh",
            "country_code": "IN"
        },
        "images": [
            {
                "about": "All",
                "link": "https://lh5.googleusercontent.com/p/AF1QipPlS34uIc3f_gUtG-BRhlit8iqflighV31Rtm3b=w397-h298-k-no"
            },
            {
                "about": "Dome",
                "link": "https://lh5.googleusercontent.com/p/AF1QipMGk2iKO7288eeetGk0gjkLD09ieNewOMhLm_vy=w224-h298-k-no"
            },
            {
                "about": "Street View & 360deg",
                "link": "https://streetviewpixels-pa.googleapis.com/v1/thumbnail?panoid=mjFcTGOfC4h0YlDcfOlQ7w&cb_client=maps_sv.tactile.gps&w=224&h=298&yaw=224.90454&pitch=0&thumbfov=100"
            }
        ],
        "link": "https://www.google.com/maps/place/Masjid+Padayan/data=!4m7!3m6!1s0x399bfdd99e0a24a5:0x9f0a70def154e6a3!8m2!3d26.8489284!4d80.9246228!16s%2Fg%2F11h7bzdqm0!19sChIJpSQKntn9mzkRo-ZU8d5wCp8?authuser=0&hl=en&rclk=1",
        "coordinates": {
            "latitude": 26.8489284,
            "longitude": 80.9246228
        }
    },
    {
        "name": "Al Makkah Masjid",
        "main_category": "Mosque",
        "address": "Al Makkah Masjid, Vicky Restaurant, Lakshman Prasad Road, Lakshman Parsad Road, Wazirganj, Lucknow, Uttar Pradesh 226018",
        "detailed_address": {
            "ward": "Maulviganj, Wazirganj",
            "street": "Vicky Restaurant, Lakshman Prasad Road, Lakshman Parsad Road",
            "city": "Lucknow",
            "postal_code": "226018",
            "state": "Uttar Pradesh",
            "country_code": "IN"
        },
        "images": [
            {
                "about": "All",
                "link": "https://lh5.googleusercontent.com/p/AF1QipO05btr6fQ6QGB1N8Totb6OIhB9cI4QLGjPfxAd=w224-h398-k-no"
            },
            {
                "about": "Street View & 360deg",
                "link": "https://streetviewpixels-pa.googleapis.com/v1/thumbnail?panoid=6WYlwUAwVIvNopgd8ZYrpA&cb_client=maps_sv.tactile.gps&w=224&h=298&yaw=304.61197&pitch=0&thumbfov=100"
            }
        ],
        "link": "https://www.google.com/maps/place/Al+Makkah+Masjid/data=!4m7!3m6!1s0x399bfd8ba4dac143:0x9f1098195e7e3a6e!8m2!3d26.8544294!4d80.9222342!16s%2Fg%2F11fjqk0wrn!19sChIJQ8HapIv9mzkRbjp-XhmYEJ8?authuser=0&hl=en&rclk=1",
        "coordinates": {
            "latitude": 26.854429399999997,
            "longitude": 80.92223419999999
        }
    },
    {
        "name": "Masjid Umar",
        "main_category": "Mosque",
        "address": "Masjid Umar, 432/107, Yaseen Ganj, Chowk, Lucknow, Uttar Pradesh 226003",
        "detailed_address": {
            "ward": "Yaseen Ganj, Chowk",
            "street": "432/107",
            "city": "Lucknow",
            "postal_code": "226003",
            "state": "Uttar Pradesh",
            "country_code": "IN"
        },
        "images": [],
        "link": "https://www.google.com/maps/place/Masjid+Umar/data=!4m7!3m6!1s0x399bffeb7b107c69:0x7ead92815893809a!8m2!3d26.8650148!4d80.8839645!16s%2Fg%2F11p51nxbqz!19sChIJaXwQe-v_mzkRmoCTWIGSrX4?authuser=0&hl=en&rclk=1",
        "coordinates": {
            "latitude": 26.865014799999997,
            "longitude": 80.88396449999999
        }
    },
    {
        "name": "Tajushsharia Masjid",
        "main_category": "Mosque",
        "address": "R72Q+RHQ Tajushsharia Masjid, Makhdoompur, P.O Tungi, Wazirganj Distt, Jumuanwan, Bihar",
        "detailed_address": {
            "ward": null,
            "street": "R72Q+RHQ, Makhdoompur, P.O Tungi, Wazirganj Distt",
            "city": "Jumuanwan",
            "postal_code": null,
            "state": "Bihar",
            "country_code": "IN"
        },
        "images": [
            {
                "about": "All",
                "link": "https://lh5.googleusercontent.com/p/AF1QipN2fICh4ddgIukTZTDdvbG-27Kf2SfEUnNsXpMM=w397-h298-k-no"
            }
        ],
        "link": "https://www.google.com/maps/place/Tajushsharia+Masjid/data=!4m7!3m6!1s0x39f31fa5d7fed029:0x568c5079f162da07!8m2!3d24.8020751!4d85.2889809!16s%2Fg%2F11ng55t_g2!19sChIJKdD-16Uf8zkRB9pi8XlQjFY?authuser=0&hl=en&rclk=1",
        "coordinates": {
            "latitude": 24.8020751,
            "longitude": 85.2889809
        }
    },
    {
        "name": "Moti Masjid, Wazirganj Lucknow",
        "main_category": "Mosque",
        "address": "VW4C+98V Moti Masjid, Wazirganj Lucknow, Layman Prasad Rd, Maulviganj, Wazirganj, Lucknow, Uttar Pradesh 226018",
        "detailed_address": {
            "ward": "Maulviganj, Wazirganj",
            "street": "VW4C+98V, Layman Prasad Rd",
            "city": "Lucknow",
            "postal_code": "226018",
            "state": "Uttar Pradesh",
            "country_code": "IN"
        },
        "images": [
            {
                "about": "All",
                "link": "https://streetviewpixels-pa.googleapis.com/v1/thumbnail?panoid=IZex-cwriRG1m_pnSbhg2w&cb_client=maps_sv.tactile.gps&w=224&h=298&yaw=230.83159&pitch=0&thumbfov=100"
            },
            {
                "about": "Street View & 360deg",
                "link": "https://streetviewpixels-pa.googleapis.com/v1/thumbnail?panoid=IZex-cwriRG1m_pnSbhg2w&cb_client=maps_sv.tactile.gps&w=224&h=298&yaw=230.83159&pitch=0&thumbfov=100"
            }
        ],
        "link": "https://www.google.com/maps/place/Moti+Masjid,+Wazirganj+Lucknow/data=!4m7!3m6!1s0x399bfd7514a7d8e3:0x86620095a9b8991e!8m2!3d26.8559953!4d80.9207988!16s%2Fg%2F11shpcb7tw!19sChIJ49inFHX9mzkRHpm4qZUAYoY?authuser=0&hl=en&rclk=1",
        "coordinates": {
            "latitude": 26.8559953,
            "longitude": 80.9207988
        }
    },
    {
        "name": "Masjid-e-khamsa",
        "main_category": "Mosque",
        "address": "Masjid-e-khamsa, 133, M.n. Abdi Marg, Maulviganj, Wazirganj, Lucknow, Uttar Pradesh 226018",
        "detailed_address": {
            "ward": "Maulviganj, Wazirganj",
            "street": "133, M.n. Abdi Marg",
            "city": "Lucknow",
            "postal_code": "226018",
            "state": "Uttar Pradesh",
            "country_code": "IN"
        },
        "images": [
            {
                "about": "All",
                "link": "https://lh5.googleusercontent.com/p/AF1QipPG9qMHEh_Ewfy8O3ay6_a5c-Gf4yyKxsSXkAPv=w529-h298-k-no"
            }
        ],
        "link": "https://www.google.com/maps/place/Masjid-e-khamsa/data=!4m7!3m6!1s0x399bfd2cd6312f95:0x9a07d66c76217ffa!8m2!3d26.8536718!4d80.923372!16s%2Fg%2F11fk1bhj3c!19sChIJlS8x1iz9mzkR-n8hdmzWB5o?authuser=0&hl=en&rclk=1",
        "coordinates": {
            "latitude": 26.853671799999997,
            "longitude": 80.923372
        }
    },
    {
        "name": "Maulana Anwar Ahmad Sahab Masjid",
        "main_category": "Mosque",
        "address": "VW3F+C7H Maulana Anwar Ahmad Sahab Masjid, Golaganj, Maulviganj, Wazirganj, Lucknow, Uttar Pradesh 226018",
        "detailed_address": {
            "ward": "Golaganj, Maulviganj, Wazirganj",
            "street": "VW3F+C7H",
            "city": "Lucknow",
            "postal_code": "226018",
            "state": "Uttar Pradesh",
            "country_code": "IN"
        },
        "images": [],
        "link": "https://www.google.com/maps/place/Maulana+Anwar+Ahmad+Sahab+Masjid/data=!4m7!3m6!1s0x399bfdfa111b8e81:0x3a09dfca8962de44!8m2!3d26.853562!4d80.9232366!16s%2Fg%2F11jskx1zl2!19sChIJgY4bEfr9mzkRRN5iicrfCTo?authuser=0&hl=en&rclk=1",
        "coordinates": {
            "latitude": 26.853562,
            "longitude": 80.9232366
        }
    },
    {
        "name": "Masjid Haider Mirza",
        "main_category": "Mosque",
        "address": "Masjid Haider Mirza, 278/121, Golaganj, Maulviganj, Wazirganj, Lucknow, Uttar Pradesh 226018",
        "detailed_address": {
            "ward": "Golaganj, Maulviganj, Wazirganj",
            "street": "278/121",
            "city": "Lucknow",
            "postal_code": "226018",
            "state": "Uttar Pradesh",
            "country_code": "IN"
        },
        "images": [
            {
                "about": "All",
                "link": "https://lh5.googleusercontent.com/p/AF1QipMT4Br7Svl0Vh-Q1f7Dr8jbZKEG74ltVzeHxlj_=w224-h309-k-no"
            },
            {
                "about": "Latest",
                "link": "https://lh5.googleusercontent.com/p/AF1QipP1qTtRIoS1Oz-YIF2LmDY-2VXWNbUdE_BNREIa=w529-h298-k-no"
            },
            {
                "about": "Videos",
                "link": "https://lh5.googleusercontent.com/p/AF1QipP1qTtRIoS1Oz-YIF2LmDY-2VXWNbUdE_BNREIa=w529-h298-k-no"
            },
            {
                "about": "Dome",
                "link": "https://lh5.googleusercontent.com/p/AF1QipPf-kI4qriHYic6tOiZGSEsIhhSmLYYfbhSmBR6=w224-h497-k-no"
            }
        ],
        "link": "https://www.google.com/maps/place/Masjid+Haider+Mirza/data=!4m7!3m6!1s0x399bfd67255ac85d:0x36573c1ffb098dd3!8m2!3d26.8523681!4d80.9237855!16s%2Fg%2F11s9b_cc33!19sChIJXchaJWf9mzkR040J-x88VzY?authuser=0&hl=en&rclk=1",
        "coordinates": {
            "latitude": 26.8523681,
            "longitude": 80.9237855
        }
    },
    {
        "name": "Sayyad Hashim Shaheed(Sunni Masjid",
        "main_category": "Mosque",
        "address": "VW3F+FRJ Sayyad Hashim Shaheed(Sunni Masjid, Maulviganj, Wazirganj, Hallaur, Lucknow, Uttar Pradesh 226018",
        "detailed_address": {
            "ward": "Maulviganj, Wazirganj",
            "street": "VW3F+FRJ",
            "city": "Hallaur, Lucknow",
            "postal_code": "226018",
            "state": "Uttar Pradesh",
            "country_code": "IN"
        },
        "images": [],
        "link": "https://www.google.com/maps/place/Sayyad+Hashim+Shaheed%28Sunni+Masjid/data=!4m7!3m6!1s0x399bfdfd35b52013:0x6c91e679120e195b!8m2!3d26.8536359!4d80.9245151!16s%2Fg%2F11rvb8vj72!19sChIJEyC1Nf39mzkRWxkOEnnmkWw?authuser=0&hl=en&rclk=1",
        "coordinates": {
            "latitude": 26.8536359,
            "longitude": 80.9245151
        }
    },
    {
        "name": "Chhoti masjid",
        "main_category": "Mosque",
        "address": "Chhoti masjid, 193/34, Wazirganj, Lucknow, Uttar Pradesh 226018",
        "detailed_address": {
            "ward": "Wazirganj",
            "street": "193/34",
            "city": "Lucknow",
            "postal_code": "226018",
            "state": "Uttar Pradesh",
            "country_code": "IN"
        },
        "images": [
            {
                "about": "All",
                "link": "https://lh5.googleusercontent.com/p/AF1QipNKhN_ifzEFrzhk_BGnp9PW5bc44CkEybfDBrsu=w224-h398-k-no"
            }
        ],
        "link": "https://www.google.com/maps/place/Chhoti+masjid/data=!4m7!3m6!1s0x399bfda21d0f7695:0x1ef5b9998330ea8e!8m2!3d26.8557259!4d80.91819!16s%2Fg%2F11khs238_n!19sChIJlXYPHaL9mzkRjuowg5m59R4?authuser=0&hl=en&rclk=1",
        "coordinates": {
            "latitude": 26.8557259,
            "longitude": 80.91819
        }
    },
    {
        "name": "Masjid usmania",
        "main_category": "Mosque",
        "address": "Masjid usmania, 182/5, Lallumal Mandir Rd, Patthar Wali Gali, Astabal Charbagh, Mashak Ganj, Wazirganj, Lucknow, Uttar Pradesh 226018",
        "detailed_address": {
            "ward": "Patthar Wali Gali, Astabal Charbagh, Mashak Ganj, Wazirganj",
            "street": "182/5, Lallumal Mandir Rd",
            "city": "Lucknow",
            "postal_code": "226018",
            "state": "Uttar Pradesh",
            "country_code": "IN"
        },
        "images": [],
        "link": "https://www.google.com/maps/place/Masjid+usmania/data=!4m7!3m6!1s0x399bfddd97a1ad61:0xbe6612bd4cb4f20a!8m2!3d26.8537973!4d80.9172266!16s%2Fg%2F11mpcv3lr9!19sChIJYa2hl939mzkRCvK0TL0SZr4?authuser=0&hl=en&rclk=1",
        "coordinates": {
            "latitude": 26.8537973,
            "longitude": 80.91722659999999
        }
    },
    {
        "name": "Masjid Bilal",
        "main_category": "Mosque",
        "address": "VW3C+844 Masjid Bilal, Badrinath Rd, Golaganj, Wazirganj, Lucknow, Uttar Pradesh 226018",
        "detailed_address": {
            "ward": "Golaganj, Wazirganj",
            "street": "VW3C+844, Badrinath Rd",
            "city": "Lucknow",
            "postal_code": "226018",
            "state": "Uttar Pradesh",
            "country_code": "IN"
        },
        "images": [],
        "link": "https://www.google.com/maps/place/Masjid+Bilal/data=!4m7!3m6!1s0x399bfd3ac208e68f:0x968e32ea10345c90!8m2!3d26.8532608!4d80.9203235!16s%2Fg%2F11td3f59cj!19sChIJj-YIwjr9mzkRkFw0EOoyjpY?authuser=0&hl=en&rclk=1",
        "coordinates": {
            "latitude": 26.853260799999997,
            "longitude": 80.9203235
        }
    },
    {
        "name": "ttiile vaalii msjid",
        "main_category": "Mosque",
        "address": "RWXF+MCF ttiile vaalii msjid, TEELA SHAH PEER MOHAAMD, 226003",
        "detailed_address": {
            "ward": "Maulviganj, Wazirganj",
            "street": "RWXF+MCF, TEELA SHAH PEER MOHAAMD",
            "city": "Lucknow",
            "postal_code": "226003",
            "state": "Uttar Pradesh",
            "country_code": "IN"
        },
        "images": [
            {
                "about": "All",
                "link": "https://streetviewpixels-pa.googleapis.com/v1/thumbnail?panoid=-w41LDvzZ3G4_zMZnjGJiQ&cb_client=maps_sv.tactile.gps&w=224&h=298&yaw=18.921953&pitch=0&thumbfov=100"
            },
            {
                "about": "Street View & 360deg",
                "link": "https://streetviewpixels-pa.googleapis.com/v1/thumbnail?panoid=-w41LDvzZ3G4_zMZnjGJiQ&cb_client=maps_sv.tactile.gps&w=224&h=298&yaw=18.921953&pitch=0&thumbfov=100"
            }
        ],
        "link": "https://www.google.com/maps/place/%E0%A4%9F%E0%A5%80%E0%A4%B2%E0%A5%87+%E0%A4%B5%E0%A4%BE%E0%A4%B2%E0%A5%80+%E0%A4%AE%E0%A4%B8%E0%A5%8D%E0%A4%9C%E0%A4%BF%E0%A4%A6/data=!4m7!3m6!1s0x399bfd06c30438bf:0xa7312bbcec6fbdc4!8m2!3d26.8491938!4d80.9235448!16s%2Fg%2F11rsg2bjnw!19sChIJvzgEwwb9mzkRxL1v7LwrMac?authuser=0&hl=en&rclk=1",
        "coordinates": {
            "latitude": 26.8491938,
            "longitude": 80.9235448
        }
    },
    {
        "name": "Masjid-e-IBNE HAZRAT ABU TALIB",
        "main_category": "Mosque",
        "address": "Masjid-e-IBNE HAZRAT ABU TALIB, GwynneRoad, Near Hanuman Temple, A-6, Gwynne Rd, Maulviganj, Aminabad, Lucknow, Uttar Pradesh 226018",
        "detailed_address": {
            "ward": "Maulviganj, Aminabad",
            "street": "GwynneRoad, Near Hanuman Temple, A-6, Gwynne Rd",
            "city": "Lucknow",
            "postal_code": "226018",
            "state": "Uttar Pradesh",
            "country_code": "IN"
        },
        "images": [
            {
                "about": "All",
                "link": "https://lh5.googleusercontent.com/p/AF1QipMe5ecb8kuFWXrM6cQcroQdRanSVPavD9Cbp_5l=w224-h398-k-no"
            },
            {
                "about": "Street View & 360deg",
                "link": "https://streetviewpixels-pa.googleapis.com/v1/thumbnail?panoid=cTvhi36AXmjHpBJY4CtZcg&cb_client=maps_sv.tactile.gps&w=224&h=298&yaw=283.93512&pitch=0&thumbfov=100"
            }
        ],
        "link": "https://www.google.com/maps/place/Masjid-e-IBNE+HAZRAT+ABU+TALIB/data=!4m7!3m6!1s0x399bfd839dc87935:0x104b5d0e28bdf279!8m2!3d26.8522434!4d80.9253727!16s%2Fg%2F11g_tgl9jd!19sChIJNXnInYP9mzkRefK9KA5dSxA?authuser=0&hl=en&rclk=1",
        "coordinates": {
            "latitude": 26.8522434,
            "longitude": 80.9253727
        }
    }
]